Workbook

Sheet Fact_Shipments
A1: ITM Summary Actual + Deviasi
A2: No | B2: Year | C2: Month Num | D2: Month Name | E2: Load_Port | F2: Company | G2: Vessel Name | H2: Shipment | I2: Quantity MT | J2: Revenue USD | K2: Demurrage USD | L2: Margin Uplift | M2: Bonus Penalty USD | N2: SSO_Flag | O2: SSO_Presentase | P2: SSO_Desc
A3: 1 | B3: 2026 | C3: 46204 | D3: 46143 | E3: BoCT | F3: EBP | G3: MV. HABCO VELA | H3: BBS PLNBN (4600GAR/TS 1.5% max) | I3: 55000 | J3: 2264350 | K3: 0 | L3: -675935.76 | M3: 0 | N3: 1 | O3: 1 | P3: =IF(N3=1, "implements", "non-implements") -> implements
A4: 2 | B4: 2026 | C4: 46204 | D4: 46143 | E4: BoCT | F4: EBP | G4: MV. VINCA | H4: MARUBENI-TOSOH (JFY2024) | I4: 44200 | J4: 6212752 | K4: -177173.23 | L4: 752606.99 | M4: -64532 | N4: 1 | O4: 1 | P4: =IF(N4=1, "implements", "non-implements") -> implements
A5: 3 | B5: 2026 | C5: 46204 | D5: 46143 | E5: BoCT | F5: EBP | G5: MV. KM SINGAPORE | H5: CHINA BAI GUI (XINDIAN 2022- 5200NAR/TS rej 2.2%) | I5: 77000 | J5: 7197190 | K5: 5677.0833 | L5: -382341.93 | M5: -199430 | N5: 1 | O5: 1 | P5: =IF(N5=1, "implements", "non-implements") -> implements
A6: 4 | B6: 2026 | C6: 46204 | D6: 46143 | E6: BoCT | F6: EBP | G6: MV. KENCANA BARUNA | H6: TJ JATI IMM (2025 NEW) | I6: 67016 | J6: 3508957.8 | K6: -1391.2827 | L6: -296938.84 | M6: 0 | N6: 1 | O6: 1 | P6: =IF(N6=1, "implements", "non-implements") -> implements
A7: 5 | B7: 2026 | C7: 46204 | D7: 46143 | E7: BoCT | F7: IMM | G7: MV. XIN HAI TONG 810 | H7: TENAGA NATIONAL BERHAD (5523 GAR) | I7: 78700 | J7: 7892823 | K7: -22107.222 | L7: 2094872.4 | M7: 390352 | N7: 1 | O7: 1 | P7: =IF(N7=1, "implements", "non-implements") -> implements
A8: 6 | B8: 2026 | C8: 46204 | D8: 46143 | E8: BoCT | F8: EBP | G8: MV. VIET THUAN 80-06 | H8: CHINA BAI GUI (XINDIAN 2022- 5200NAR/TS rej 2.2%) | I8: 73600 | J8: 6849216 | K8: -35430 | L8: -498232.23 | M8: -170016 | N8: 1 | O8: 1 | P8: =IF(N8=1, "implements", "non-implements") -> implements
A9: 7 | B9: 2026 | C9: 46204 | D9: 46143 | E9: BoCT | F9: EBP | G9: MV. LUMOSO KARUNIA VIII | H9: BBS PLNBN (4600GAR/TS 1.5% max) | I9: 52000 | J9: 2140840 | K9: 0 | L9: -695984.68 | M9: 0 | N9: 0 | O9: 0 | P9: =IF(N9=1, "implements", "non-implements") -> non-implements
A10: 8 | B10: 2026 | C10: 46204 | D10: 46143 | E10: BoCT | F10: EBP | G10: MV. SINCERE SMART | H10: SHENHUA (5200NAR/TS max 2.0%) | I10: 64999 | J10: 6227554.2 | K10: -5725.125 | L10: -360876.16 | M10: 29899.54 | N10: 1 | O10: 1 | P10: =IF(N10=1, "implements", "non-implements") -> implements
A11: 9 | B11: 2026 | C11: 46204 | D11: 46143 | E11: BoCT | F11: EBP | G11: MV. LUMOSO PRATAMA | H11: TJ JATI IMM (2025 NEW) | I11: 67007 | J11: 3452200.6 | K11: -16389.005 | L11: -367957.73 | M11: 0 | N11: 1 | O11: 1 | P11: =IF(N11=1, "implements", "non-implements") -> implements
A12: 10 | B12: 2026 | C12: 46204 | D12: 46143 | E12: BoCT | F12: EBP | G12: MV. KARTINI BARUNA | H12: TJ JATI IMM (2025 NEW) | I12: 67023 | J12: 3476483 | K12: 6950.0162 | L12: -321338.26 | M12: 0 | N12: 1 | O12: 1 | P12: =IF(N12=1, "implements", "non-implements") -> implements
A13: 11 | B13: 2026 | C13: 46204 | D13: 46143 | E13: BoCT | F13: EBP | G13: MV. JIN NING 7 | H13: CHINA BAI GUI (XINDIAN) - 4450NAR/TS(max) 1.7% | I13: 63050 | J13: 4852328 | K13: -14791.944 | L13: -601610.36 | M13: -54223 | N13: 0 | O13: 0 | P13: =IF(N13=1, "implements", "non-implements") -> non-implements
A14: 12 | B14: 2026 | C14: 46204 | D14: 46143 | E14: BoCT | F14: EBP | G14: MV. ARIMBI BARUNA | H14: TJ JATI IMM (2025 NEW) | I14: 67006 | J14: 3472250.9 | K14: 7918.9648 | L14: -323623.12 | M14: 0 | N14: 1 | O14: 1 | P14: =IF(N14=1, "implements", "non-implements") -> implements
... A50: 48 | B50: 2026 | C50: 46204 | D50: 46143 | E50: Bunyut | F50: TCM | G50: BG. MJL 308 | H50: INDOCEMENT (2024) | I50: 7608.13 | J50: 716914.09 | K50: 0 | L50: 28996.141 | M50: 0 | N50: 1 | O50: 1 | P50: =IF(N50=1, "implements", "non-implements") -> implements

Sheet Sheet1
B1: Total Kapal | C1: Total Kapal BoCT | D1: Total Kapal Mahakam | E1: Total Throughput | F1: Total Revenue | G1: Total Demurrage | H1: Total Margin Lift | I1: Total Bonus Penalty | J1: Total SSO_Flag | K1: Boct | L1: Mahakam | M1: Implementation | N1: Non-Implementation | O1: Type | P1: Demurrage Value | Q1: Dem $/ton
B2: =ROWS(Fact_Shipments!H3:H50) -> 48 | C2: =COUNTIF(Fact_Shipments!E2:E50,"BOCT") -> 26 | D2: =COUNTIF(Fact_Shipments!E3:E50,"<>boct") -> 22 | E2: =SUM(Fact_Shipments!I3:I50) -> 2432361.1 | F2: =SUM(Fact_Shipments!J3:J50) -> 2.4132687e+08 | G2: =SUM(Fact_Shipments!K3:K50) -> -617120.69 | H2: =SUM(Fact_Shipments!L3:L50) -> 10680360 | I2: =SUM(Fact_Shipments!M3:M50)* -1 -> -2648983.8 | J2: =SUM(Fact_Shipments!N3:N50) -> 44 | K2: =J2/C2*100 -> 169.23077 | L2: =J2/D2*100 -> 200 | M2: =J2/B2*100 -> 91.666667 | N2: =(B2-J2)/B2*100 -> 8.3333333 | O2: BoCT | P2: -4.2472754 | Q2: 0.19305797
O3: Mahakam | P3: =SUMIF(Fact_Shipments!E3:E50,"<>BoCT",Fact_Shipments!K3:K50) * -1 -> 336486.56 | Q3: 0.37950283
O4: Total | P4: =SUM(P2:P3) -> 336482.31 | Q4: 0.31060467

Sheet Summary_Baseline
A1: Summary Loading of ITM Shipment 2023
A2: Calculation Sheet
B3: Jul
B4: Shipment | J4: ETA/ATA, ETB, and ETD | N4: IMM | O4: IMM | P4: IMM | Q4: IMM | R4: IMM | S4: TCM | T4: TCM | U4: BEK | V4: BEK | W4: BEK | X4: JBG | Y4: GPK | Z4: NPR | AA4: NPR | AB4: TIS | AC4: EBP | AD4: EBP | AE4: EBP | AF4: EBP | AG4: EBP | AH4: EBP | AI4: EBP | AJ4: EBP | AK4: EBP | AL4: EBP | AM4: EBP | AN4: EBP | AO4: EBP | AP4: EBP | AQ4: EBP | AR4: EBP | AS4: EBP | AT4: EBP | AU4: EBP | AV4: EBP | AW4: EBP | AX4: EBP | AY4: EBP | AZ4: EBP | BA4: EBP | BB4: EBP | BC4: EBP | BD4: EBP | BE4: EBP | BF4: EBP | BG4: EBP | BH4: EBP | BI4: EBP | BJ4: Total | BL4: Laycan | BO4: Shipper | BQ4: Status | BS4: Name | BU4: Result: Coal quality by property | CF4: Penalty | CN4: Demurrage | CV4: Shipment | CX4: Value Coal Blended (FOB) | DF4: FOB | DG4: FOB | DH4: FOB | DI4: FOB | DJ4: FOB | DK4: FOB | DL4: FOB | DM4: FOB | DN4: FOB | DO4: FOB | DP4: FOB | DQ4: FOB | DR4: FOB | DS4: FOB | DT4: FOB | DU4: FOB | DV4: FOB | DW4: FOB | DX4: FOB | DY4: FOB | DZ4: FOB | EA4: FOB | EB4: FOB | EC4: FOB | ED4: FOB | EE4: FOB | EF4: FOB | EH4: FOB | EI4: FOB | EJ4: FOB | EK4: FOB | EL4: FOB | EM4: FOB | EN4: FOB | EO4: FOB | EP4: FOB | EQ4: FOB | ER4: FOB | ES4: FOB | ET4: FOB | EU4: FOB | EV4: FOB | EW4: FOB | EX4: FOB | EY4: FOB | EZ4: FOB | FA4: FOB | FB4: FOB | FC4: FOB | FD4: FOB | FE4: FOB | FF4: FOB | FG4: FOB | FH4: FOB | FJ4: Cost to Vessel (Operation) | FR4: GLR | FU4: FOB Price | FV4: Shipment Price | FW4: Bonus/Penalty | FX4: Revenue | FY4: Demurrage | FZ4: Barging Cost | GA4: Cash Cost to Vessel | GB4: FLF Cost | GC4: Royalty | GD4: Agency | GE4: Surveyor | GF4: Total Cost | GG4: Total Cost | GH4: Margin | GI4: Margin | GK4: HBA
B5: No. | C5: Month | D5: Company | E5: Name of Vessel | F5: Buyer | G5: End user | H5: Load Port | J5: ETA/ATA | K5: ETB | L5: ETD | N5: IMM-WB.HCV.LS | O5: IMM-WB.HCV.HS | P5: IMM-EB.MCV.LS | Q5: IMM-EB.MCV.MS | R5: IMM-EB.MCV.HS | S5: TCM.HCV.LS | T5: TCM.HCV.HS | U5: BEK.HCV.LS | V5: BEK.HCV.HS | W5: BEK.MCV.LS | X5: JBG | Y5: GPK | Z5: NPR.MCV.LS | AA5: NPR.MCV.HS | AB5: TIS | AC5: EBH.HCV | AD5: SHORE.HCV | AE5: KMIA.MCV.LS | AF5: BBE.MCV | AG5: MBL.MCV | AH5: MBL.56.MCV | AI5: GHP.MCV | AJ5: EMJ.MCV | AK5: EMJ.MCV | AL5: KBM.MCV | AM5: IKJ.MCV | AN5: PUMA MCV | AO5: AUB | AP5: MKE.LCV | AQ5: KJA.LCV.LS | AR5: JHN.LCV | AS5: DMP.LCV | AT5: MCM.LCV | AU5: BMM.LCV | AV5: GIE.LCV | AW5: HWA.LCV | AX5: BBA.LCV | AY5: MML.LCV | AZ5: NEI.LCV | BA5: DJA.LCV | BB5: KPM.LCV | BC5: KJM.LCV | BD5: DBP.LCV | BE5: DMP | BF5: BBS 34 | BG5: BUM.LCV | BH5: IWBM.LCV | BI5: BISM.LCV | BJ5: Total | BL5: Lay | BM5: can | BO5: % | BQ5: Status | BS5: FLF | BU5: TM (AR) | BV5: M (AD) | BW5: ASH (AD) | BX5: ASH (AR) | BY5: TS (AD) | BZ5: TS (AR) | CA5: CV (AD) | CB5: CV (AR) | CC5: CV (NAR) | CF5: W0 | CG5: W1 | CH5: W2 | CI5: W3 | CJ5: W4 | CK5: W5 | CL5: Act | CN5: W0 | CO5: W1 | CP5: W2 | CQ5: W3 | CR5: W4 | CS5: W5 | CT5: Act | CV5: Price ($) | CX5: W0 | CY5: W1 | CZ5: W2 | DA5: W3 | DB5: W4 | DC5: W5 | DD5: Act | DF5: IMM WB HCV LS | DG5: IMM WB HCV HS | DH5: IMM EB MCV LS | DI5: IMM EB MCV MS | DJ5: IMM EB MCV HS | DK5: IMMEAST SupHS | DL5: TCM HCV LS | DM5: TCM HCV HS | DN5: TCM HCV MS | DO5: BEK MCV LS | DP5: BEK MCV MS | DQ5: EMB | DR5: JBG | DS5: IKJ | DT5: BBA | DU5: IDX | DV5: KMIA | DW5: BBE | DX5: BP | DY5: KEI | DZ5: KJA | EA5: KBM | EB5: ALH | EC5: DUM | ED5: JHN | EE5: LSP | EF5: PIDI | EH5: IMM WB HCV LS | EI5: IMM WB HCV HS | EJ5: IMM EB MCV LS | EK5: IMM EB MCV MS | EL5: IMM EB MCV HS | EM5: IMMEAST SupHS | EN5: TCM HCV LS | EO5: TCM HCV HS | EP5: TCM HCV MS | EQ5: BEK MCV LS | ER5: BEK MCV MS | ES5: EMB | ET5: JBG | EU5: IKJ | EV5: BBA | EW5: IDX | EX5: KMIA | EY5: BBE | EZ5: BP | FA5: KEI | FB5: KJA | FC5: KBM | FD5: ALH | FE5: DUM | FF5: JHN | FG5: LSP | FH5: PIDI | FJ5: W0 | FK5: W1 | FL5: W2 | FM5: W3 | FN5: W4 | FO5: W5 | FP5: Act | FR5: TPH | FU5: $/ton | FV5: $ | FW5: $ | FX5: $ | FY5: $ | FZ5: $ | GA5: $ | GC5: $ | GD5: $ | GE5: $ | GF5: $ | GG5: $/ton | GH5: $ | GI5: $/ton | GK5: Class
B6: 1 | C6: 46204 | D6: EBP | E6: MV. HABCO VELA | F6: BBS PLNBN (4600GAR/TS 1.5% max) | G6: PLNBN JUN #06 | H6: BoCT | J6: 46201 | K6: 46203.375 | L6: 46204.807 | R6: 24998 | AT6: 7500 | BI6: 22502 | BJ6: 55000 | BL6: 46200 | BM6: 46209 | BO6: 0.54549091 | BQ6: Plan | BU6: 33.03083 | BV6: 13.622765 | BW6: 6.3617722 | BX6: 4.8673454 | BY6: 1.2044698 | BZ6: 1.1071121 | CA6: 5683.9808 | CB6: 4463.7861 | CC6: 4105.5629 | CF6: 0 | CN6: 0 | FR6: 1600 | FU6: 40.352003 | FV6: 2219360.1 | FW6: 0 | FX6: 2219360.1 | FY6: 0 | FZ6: 0 | GA6: -2756729.4 | GB6: -165000 | GC6: 0 | GD6: -8877.4406 | GE6: -7150 | GF6: -2937756.8 | GG6: -53.41376 | GH6: -718396.69 | GI6: -13.061758 | GK6: HBA II
B7: 2 | C7: 46204 | D7: EBP | E7: MV. VINCA | F7: MARUBENI-TOSOH (JFY2024) | G7: TOSOH #03 | H7: BoCT | J7: 46193.312 | K7: 46204.953 | L7: 46205.874 | N7: 5191.47 | R7: 1500 | S7: 4500 | T7: 3000 | U7: 15000 | AB7: 7500 | AH7: 7508.53 | BJ7: 44200 | BL7: 46192 | BM7: 46201 | BO7: 0.16987624 | BQ7: Plan | BU7: 15.519742 | BV7: 9.6215492 | BW7: 4.313061 | BX7: 4.0312184 | BY7: 0.93754071 | BZ7: 0.87735591 | CA7: 6623.6967 | CB7: 6191.986 | CC7: 5904.0709 | CF7: 0.78132412 | CN7: -3.780226 | FR7: 2000 | FU7: 133.1 | FV7: 5883020 | FW7: 34534.526 | FX7: 5917554.5 | FY7: -167085.99 | FZ7: -41044.924 | GA7: -5086653.4 | GB7: -132600 | GC7: 0 | GD7: -23532.08 | GE7: -5746 | GF7: -5456662.4 | GG7: -123.4539 | GH7: 460892.15 | GI7: 10.427424 | GK7: HBA
B8: 3 | C8: 46204 | D8: IMM | E8: MV. SHANDONG FU DE | F8: TENAGA NATIONAL BERHAD (5523 GAR) | G8: TNB JIMAH #3/6 | H8: BoCT | J8: 46202 | K8: 46206.02 | L8: 46207.508 | N8: 12000 | Q8: 8000 | R8: 55000 | BJ8: 75000 | BL8: 46198 | BM8: 46207 | BO8: 1 | BQ8: Plan | BU8: 14.962667 | BV8: 11.2072 | BW8: 5.8326667 | BX8: 5.5874882 | BY8: 2.014 | BZ8: 1.9304812 | CA8: 6256.8667 | CB8: 5991.9203 | CC8: 5691.4276 | CF8: 0.72393242 | CN8: -0.54303373 | FR8: 2100 | FU8: 96.43158 | FV8: 7232368.5 | FW8: 54294.931 | FX8: 7286663.4 | FY8: -40727.53 | FZ8: 0 | GA8: -4532094.7 | GB8: 0 | GC8: -976369.75 | GD8: 0 | GE8: 0 | GF8: -5549192 | GG8: -73.989227 | GH8: 1737471.4 | GI8: 23.166285 | GK8: HBA I
B9: 4 | C9: 46204 | D9: EBP | E9: MV. KM SINGAPORE | F9: CHINA BAI GUI (XINDIAN 2022- 5200NAR/TS rej 2.2%) | G9: XINDIAN BAI GUI 5200NAR #10/19 | H9: BoCT | J9: 46204.5 | K9: 46207.654 | L9: 46209.258 | R9: 64295.05 | Y9: 7500 | AX9: 5204.95 | BJ9: 77000 | BL9: 46196 | BM9: 46205 | BO9: 0.067596753 | BQ9: Plan | BU9: 19.824883 | BV9: 12.666229 | BW9: 6.2371373 | BX9: 5.7214342 | BY9: 1.98983 | BZ9: 1.9012111 | CA9: 6001.6438 | CB9: 5529.4697 | CC9: 5215.599 | CF9: 0.5103345 | CN9: -0.75743081 | FR9: 2000 | FU9: 96.148936 | FV9: 7403468.1 | FW9: 39295.757 | FX9: 7442763.8 | FY9: -58322.173 | FZ9: 0 | GA9: -7314747.4 | GB9: -231000 | GC9: 0 | GD9: -29613.872 | GE9: -10010 | GF9: -7643693.5 | GG9: -99.268746 | GH9: -200929.62 | GI9: -2.6094756 | GK9: HBA I
B10: 5 | C10: 46204 | D10: EBP | E10: MV. LUMOSO KARUNIA IX | F10: FREEPORT | G10: FREEPORT #1/4 | H10: BoCT | J10: 46205 | K10: 46209.654 | L10: 46210.758 | N10: 1900 | R10: 3000 | S10: 15000 | AB10: 15000 | AH10: 7500 | AL10: 5300 | AS10: 5300 | BJ10: 53000 | BL10: 46205 | BM10: 46214 | BO10: 0.34150943 | BQ10: Plan | BU10: 17.399358 | BV10: 9.6419515 | BW10: 4.4628844 | BX10: 4.0229677 | BY10: 1.0267823 | BZ10: 0.94600275 | CA10: 6570.4623 | CB10: 6023.9589 | CC10: 5729.501 | CF10: 1.1023547 | CN10: -1.3356974 | FR10: 2000 | FU10: 128.50712 | FV10: 6810877.3 | FW10: 58424.799 | FX10: 6869302.1 | FY10: -70791.964 | FZ10: -89755.769 | GA10: -5920886.3 | GB10: -159000 | GC10: 0 | GD10: -27243.509 | GE10: -6890 | GF10: -6274567.5 | GG10: -118.38807 | GH10: 594734.54 | GI10: 11.221406 | GK10: HBA
B11: 6 | C11: 46204 | D11: EBP | E11: MV. LUMOSO PRATAMA | F11: TJ JATI IMM (2025 NEW) | G11: TJ JATI IMM JUL #1 | H11: BoCT | J11: 46206 | K11: 46210.904 | L11: 46212.455 | R11: 52000 | Y11: 15000 | BJ11: 67000 | BL11: 46206 | BM11: 46215 | BO11: 0 | BQ11: Plan | BU11: 21.925866 | BV11: 12.656579 | BW11: 7.7223873 | BX11: 6.8841684 | BY11: 1.8935514 | BZ11: 1.7560106 | CA11: 5923.6472 | CB11: 5312.0883 | CC11: 4992.4989 | CF11: 0 | CN11: -0.96777491 | FR11: 1800 | FU11: 49.05 | FV11: 3286350 | FW11: 0 | FX11: 3286350 | FY11: -64840.919 | FZ11: 0 | GA11: -3579854.6 | GB11: -201000 | GC11: 0 | GD11: -13145.4 | GE11: -8710 | GF11: -3867550.9 | GG11: -57.72464 | GH11: -581200.89 | GI11: -8.6746401 | GK11: HBA I
B12: 7 | C12: 46204 | D12: EBP | E12: MV. TBN | F12: CHINA BAI GUI (XINDIAN 2022- 5200NAR/TS rej 2.2%) | G12: XINDIAN BAI GUI 5200NAR #11/19 | H12: BoCT | J12: 46208 | K12: 46212.85 | L12: 46214.309 | Q12: 3000 | R12: 56700 | AV12: 5300 | AX12: 5000 | BJ12: 70000 | BL12: 46208 | BM12: 46217 | BO12: 0.14714286 | BQ12: Plan | BU12: 20.14331 | BV12: 10.734332 | BW12: 7.6213463 | BX12: 6.8575564 | BY12: 2.0565017 | BZ12: 1.9025795 | CA12: 6089.2006 | CB12: 5465.5229 | CC12: 5150.473 | CF12: -0.592835 | CN12: -1.0436947 | FR12: 2000 | FU12: 96.148936 | FV12: 6730425.5 | FW12: -41498.45 | FX12: 6688927.1 | FY12: -73058.631 | FZ12: 0 | GA12: -6786679.6 | GB12: -210000 | GC12: 0 | GD12: -26921.702 | GE12: -9100 | GF12: -7105759.9 | GG12: -101.51086 | GH12: -416832.85 | GI12: -5.954755 | GK12: HBA I
B13: 8 | C13: 46204 | D13: EBP | E13: MV. TBN | F13: BBS PLNBN (4600GAR/TS 1.5% max) | G13: PLNBN JUL #01 | H13: BoCT | J13: 46210 | K13: 46214.705 | L13: 46216.137 | R13: 17500 | U13: 7500 | Y13: 15000 | BI13: 15000 | BJ13: 55000 | BL13: 46210 | BM13: 46219 | BO13: 0.27272727 | BQ13: Plan | BU13: 32.553265 | BV13: 14.728431 | BW13: 6.9485829 | BX13: 5.4493413 | BY13: 0.95686339 | BZ13: 0.85652705 | CA13: 5633.7691 | CB13: 4504.6609 | CC13: 4149.4443 | CF13: 0 | CN13: 0 | FR13: 1600 | FU13: 40.352003 | FV13: 2219360.1 | FW13: 0 | FX13: 2219360.1 | FY13: 0 | FZ13: 0 | GA13: -2824196.4 | GB13: -165000 | GC13: 0 | GD13: -8877.4406 | GE13: -7150 | GF13: -3005223.8 | GG13: -54.640433 | GH13: -785863.69 | GI13: -14.288431 | GK13: HBA II
B14: 9 | C14: 46204 | D14: EBP | E14: MV. TBN | F14: SHENHUA (5200NAR/TS max 2.0%) | G14: SHENHUA 5200NAR TS 2% #4/6 | H14: BoCT | J14: 46213 | K14: 46216.283 | L14: 46217.741 | R14: 47500 | U14: 7500 | AQ14: 7500 | AT14: 7500 | BJ14: 70000 | BL14: 46213 | BM14: 46222 | BO14: 0.21428571 | BQ14: Plan | BU14: 20.961608 | BV14: 11.564132 | BW14: 6.7155433 | BX14: 6.0728477 | BY14: 1.7077996 | BZ14: 1.5850945 | CA14: 6056.6578 | CB14: 5429.1287 | CC14: 5109.1173 | CF14: -0.8935325 | CN14: -0.64056973 | FR14: 2000 | FU14: 96.648936 | FV14: 6765425.5 | FW14: -62547.275 | FX14: 6702878.3 | FY14: -44839.881 | FZ14: -31821.533 | GA14: -6728575.4 | GB14: -210000 | GC14: 0 | GD14: -27061.702 | GE14: -9100 | GF14: -7051398.5 | GG14: -100.73426 | GH14: -348520.21 | GI14: -4.9788602 | GK14: HBA I
B15: 10 | C15: 46204 | D15: EBP | E15: MV. TBN | F15: BBS PLNBN (4600GAR/TS 1.5% max) | G15: PLNBN JUL #02 | H15: BoCT | J15: 46215 | K15: 46217.887 | L15: 46219.319 | R15: 2500 | U15: 7500 | V15: 15000 | Y15: 7500 | BI15: 22500 | BJ15: 55000 | BL15: 46215 | BM15: 46224 | BO15: 0.40909091 | BQ15: Plan | BU15: 34.18144 | BV15: 14.04267 | BW15: 6.2036102 | BX15: 4.6044552 | BY15: 0.79476448 | BZ15: 0.69303991 | CA15: 5720.8214 | CB15: 4444.8959 | CC15: 4078.3674 | CF15: 0 | CN15: 0 | FR15: 1600 | FU15: 40.352003 | FV15: 2219360.1 | FW15: 0 | FX15: 2219360.1 | FY15: 0 | FZ15: 0 | GA15: -2740270.3 | GB15: -165000 | GC15: 0 | GD15: -8877.4406 | GE15: -7150 | GF15: -2921297.7 | GG15: -53.114504 | GH15: -701937.58 | GI15: -12.762501 | GK15: HBA II
B16: 11 | C16: 46204 | D16: EBP | E16: MV. BULK BATAVIA | F16: TJ JATI IMM (2025 NEW) | G16: TJ JATI IMM JUL #2 | H16: BoCT | J16: 46216 | K16: 46219.715 | L16: 46221.266 | R16: 52000 | Y16: 15000 | BJ16: 67000 | BL16: 46216 | BM16: 46225 | BO16: 0 | BQ16: Plan | BU16: 21.925866 | BV16: 12.656579 | BW16: 7.7223873 | BX16: 6.8841684 | BY16: 1.8935514 | BZ16: 1.7560106 | CA16: 5923.6472 | CB16: 5312.0883 | CC16: 4992.4989 | CF16: 0 | CN16: -0.69897867 | FR16: 1800 | FU16: 49.05 | FV16: 3286350 | FW16: 0 | FX16: 3286350 | FY16: -46831.571 | FZ16: 0 | GA16: -3579854.6 | GB16: -201000 | GC16: 0 | GD16: -13145.4 | GE16: -8710 | GF16: -3849541.5 | GG16: -57.455844 | GH16: -563191.54 | GI16: -8.4058439 | GK16: HBA I
B17: 12 | C17: 46204 | D17: EBP | E17: MV. TBN | F17: CHINA BAI GUI (XINDIAN) - 4450NAR/TS(max) 1.7% | G17: XINDIAN BAI GUI #3/7 (4450NAR) | H17: BoCT | J17: 46218 | K17: 46221.412 | L17: 46223.356 | R17: 35000 | Y17: 7500 | AQ17: 7500 | AT17: 15000 | AX17: 5000 | BJ17: 70000 | BL17: 46218 | BM17: 46227 | BO17: 0.39285714 | BQ17: Plan | BU17: 28.287132 | BV17: 13.539465 | BW17: 6.575251 | BX17: 5.5619367 | BY17: 1.2768042 | BZ17: 1.1714074 | CA17: 5748.0143 | CB17: 4792.7707 | CC17: 4454.5369 | CF17: 0.2059362 | CN17: -0.79875425 | FR17: 1500 | FU17: 79.435532 | FV17: 5560487.2 | FW17: 14415.534 | FX17: 5574902.8 | FY17: -55912.798 | FZ17: -31821.533 | GA17: -5705695.8 | GB17: -210000 | GC17: 0 | GD17: -22241.949 | GE17: -9100 | GF17: -6034772.1 | GG17: -86.21103 | GH17: -459869.33 | GI17: -6.5695619 | GK17: HBA II
B18: 13 | C18: 46204 | D18: EBP | E18: MV. TBN | F18: BBS PLNBN (4600GAR/TS 1.5% max) | G18: PLNBN JUL #03 | H18: BoCT | J18: 46220 | K18: 46223.502 | L18: 46224.934 | R18: 2500 | U18: 7500 | V18: 15000 | Y18: 7500 | BI18: 22500 | BJ18: 55000 | BL18: 46220 | BM18: 46229 | BO18: 0.40909091 | BQ18: Plan | BU18: 34.18144 | BV18: 14.04267 | BW18: 6.2036102 | BX18: 4.6044552 | BY18: 0.79476448 | BZ18: 0.69303991 | CA18: 5720.8214 | CB18: 4444.8959 | CC18: 4078.3674 | CF18: 0 | CN18: 0 | FR18: 1600 | FU18: 40.352003 | FV18: 2219360.1 | FW18: 0 | FX18: 2219360.1 | FY18: 0 | FZ18: 0 | GA18: -2740270.3 | GB18: -165000 | GC18: 0 | GD18: -8877.4406 | GE18: -7150 | GF18: -2921297.7 | GG18: -53.114504 | GH18: -701937.58 | GI18: -12.762501 | GK18: HBA II
B19: 14 | C19: 46204 | D19: EBP | E19: MV. TBN | F19: SUNNY EXPRESS (5,200NAR/ TS(rej) 2.2%) | G19: SUNNY EXPRESS #7/12 | H19: BoCT | J19: 46222 | K19: 46225.08 | L19: 46226.434 | Q19: 5000 | R19: 49700 | AV19: 5300 | AX19: 5000 | BJ19: 65000 | BL19: 46222 | BM19: 46231 | BO19: 0.15846154 | BQ19: Plan | BU19: 20.43501 | BV19: 10.77966 | BW19: 7.5892618 | BX19: 6.8093908 | BY19: 2.0063781 | BZ19: 1.8549523 | CA19: 6081.131 | CB19: 5442.3901 | CC19: 5126.6221 | CF19: -0.7109235 | CN19: -0.63952381 | FR19: 2000 | FU19: 96.148936 | FV19: 6249680.9 | FW19: -46210.028 | FX19: 6203470.8 | FY19: -41569.048 | FZ19: 0 | GA19: -6271844.1 | GB19: -195000 | GC19: 0 | GD19: -24998.723 | GE19: -8450 | GF19: -6541861.9 | GG19: -100.64403 | GH19: -338391.03 | GI19: -5.2060159 | GK19: HBA I
B20: 15 | C20: 46204 | D20: EBP | E20: MV. TBN | F20: BBS PLNBN (4600GAR/TS 1.5% max) | G20: PLNBN JUL #04 | H20: BoCT | J20: 46224 | K20: 46226.58 | L20: 46228.013 | R20: 2500 | U20: 7500 | V20: 15000 | Y20: 15000 | BI20: 15000 | BJ20: 55000 | BL20: 46224 | BM20: 46233 | BO20: 0.27272727 | BQ20: Plan | BU20: 32.830245 | BV20: 14.787684 | BW20: 6.2894522 | BX20: 4.8219919 | BY20: 0.78374219 | BZ20: 0.6909252 | CA20: 5682.803 | CB20: 4534.5213 | CC20: 4175.0441 | CF20: 0 | CN20: 0 | FR20: 1600 | FU20: 40.352003 | FV20: 2219360.1 | FW20: 0 | FX20: 2219360.1 | FY20: 0 | FZ20: 0 | GA20: -2829496.3 | GB20: -165000 | GC20: 0 | GD20: -8877.4406 | GE20: -7150 | GF20: -3010523.8 | GG20: -54.736796 | GH20: -791163.63 | GI20: -14.384793 | GK20: HBA II
B21: 16 | C21: 46204 | D21: EBP | E21: MV. KARTINI BARUNA | F21: TJ JATI IMM (2025 NEW) | G21: TJ JATI IMM JUL #3 | H21: BoCT | J21: 46226 | K21: 46228.158 | L21: 46229.709 | R21: 52000 | Y21: 15000 | BJ21: 67000 | BL21: 46220 | BM21: 46229 | BO21: 0 | BQ21: Plan | BU21: 21.925866 | BV21: 12.656579 | BW21: 7.7223873 | BX21: 6.8841684 | BY21: 1.8935514 | BZ21: 1.7560106 | CA21: 5923.6472 | CB21: 5312.0883 | CC21: 4992.4989 | CF21: 0 | CN21: -0.34695243 | FR21: 1800 | FU21: 49.05 | FV21: 3286350 | FW21: 0 | FX21: 3286350 | FY21: -23245.813 | FZ21: 0 | GA21: -3579854.6 | GB21: -201000 | GC21: 0 | GD21: -13145.4 | GE21: -8710 | GF21: -3825955.8 | GG21: -57.103818 | GH21: -539605.78 | GI21: -8.0538176 | GK21: HBA I
B22: 17 | C22: 46204 | D22: EBP | E22: MV. TBN | F22: BBS PLNBN (4600GAR/TS 1.5% max) | G22: PLNBN JUL #05 | H22: BoCT | J22: 46228 | K22: 46230.105 | L22: 46231.537 | R22: 10000 | U22: 15000 | Y22: 15000 | BI22: 15000 | BJ22: 55000 | BL22: 46228 | BM22: 46237 | BO22: 0.27272727 | BQ22: Plan | BU22: 32.499181 | BV22: 14.795597 | BW22: 6.4696974 | BX22: 5.0088597 | BY22: 0.70431687 | BZ22: 0.62196973 | CA22: 5674.7296 | CB22: 4551.3185 | CC22: 4195.1563 | CF22: 0 | CN22: 0 | FR22: 1600 | FU22: 40.352003 | FV22: 2219360.1 | FW22: 0 | FX22: 2219360.1 | FY22: 0 | FZ22: 0 | GA22: -2887562.6 | GB22: -165000 | GC22: 0 | GD22: -8877.4406 | GE22: -7150 | GF22: -3068590 | GG22: -55.792545 | GH22: -849229.86 | GI22: -15.440543 | GK22: HBA II
B23: 18 | C23: 46204 | D23: EBP | E23: MV. TBN | F23: MARUBENI-TOSOH (JFY2024) | G23: TOSOH #04 | H23: BoCT | J23: 46229 | K23: 46231.683 | L23: 46232.579 | N23: 5500 | S23: 15000 | AB23: 7500 | AH23: 7500 | AJ23: 7500 | BJ23: 43000 | BL23: 46229 | BM23: 46238 | BO23: 0.34883721 | BQ23: Plan | BU23: 16.490128 | BV23: 9.5337229 | BW23: 4.5634638 | BX23: 4.1911802 | BY23: 0.86360474 | BZ23: 0.80235625 | CA23: 6598.8442 | CB23: 6099.5468 | CC23: 5838.3833 | CF23: 1.6823431 | CN23: -0.83891196 | FR23: 2000 | FU23: 133.1 | FV23: 5723300 | FW23: 72340.753 | FX23: 5795640.8 | FY23: -36073.214 | FZ23: -72130.029 | GA23: -4937160.8 | GB23: -129000 | GC23: 0 | GD23: -22893.2 | GE23: -5590 | GF23: -5202847.3 | GG23: -120.99645 | GH23: 592793.48 | GI23: 13.785895 | GK23: HBA
B24: 19 | C24: 46204 | D24: EBP | E24: MV. TBN | F24: BBS PLNBN (4600GAR/TS 1.5% max) | G24: PLNBN AUG #01 | H24: BoCT | J24: 46231 | K24: 46232.725 | L24: 46234.157 | R24: 10000 | U24: 15000 | Y24: 15000 | BI24: 15000 | BJ24: 55000 | BL24: 46231 | BM24: 46240 | BO24: 0.27272727 | BQ24: Plan | BU24: 32.499181 | BV24: 14.795597 | BW24: 6.4696974 | BX24: 5.0088597 | BY24: 0.70431687 | BZ24: 0.62196973 | CA24: 5674.7296 | CB24: 4551.3185 | CC24: 4195.1563 | CF24: 0 | CN24: 0 | FR24: 1600 | FU24: 40.352003 | FV24: 2219360.1 | FW24: 0 | FX24: 2219360.1 | FY24: 0 | FZ24: 0 | GA24: -2887562.6 | GB24: -165000 | GC24: 0 | GD24: -8877.4406 | GE24: -7150 | GF24: -3068590 | GG24: -55.792545 | GH24: -849229.86 | GI24: -15.440543 | GK24: HBA II
B25: 20 | C25: 46204 | D25: EBP | E25: BG. TBN | F25: BBS PLNBN (4600GAR/TS 1.5% max) Barge | G25: PLNBN BARGE JUL #01 | H25: BoCT | J25: 46216 | K25: 46216 | L25: 46216.208 | R25: 3750 | BI25: 3750 | BJ25: 7500 | BO25: 0.5 | BQ25: Plan | BU25: 33.731493 | BV25: 12.925597 | BW25: 7.3018177 | BX25: 5.6063149 | BY25: 1.3276 | BZ25: 1.1891942 | CA25: 5713.6844 | CB25: 4404.0155 | CC25: 4040.9013 | CF25: 0 | CN25: 0 | FR25: 1500 | FU25: 40.352003 | FV25: 302640.02 | FW25: 0 | FX25: 302640.02 | FY25: 0 | FZ25: 0 | GA25: -356186.72 | GB25: -22500 | GC25: 0 | GD25: -1210.5601 | GE25: -975 | GF25: -380872.28 | GG25: -50.78297 | GH25: -78232.258 | GI25: -10.430968 | GK25: HBA II
B26: 21 | C26: 46204 | D26: EBP | E26: BG. TBN | F26: BBS PLNBN (4600GAR/TS 1.5% max) Barge | G26: PLNBN BARGE JUL #02 | H26: BoCT | J26: 46218 | K26: 46218 | L26: 46218.208 | R26: 3750 | BI26: 3750 | BJ26: 7500 | BO26: 0.5 | BQ26: Plan | BU26: 33.731493 | BV26: 12.925597 | BW26: 7.3018177 | BX26: 5.6063149 | BY26: 1.3276 | BZ26: 1.1891942 | CA26: 5713.6844 | CB26: 4404.0155 | CC26: 4040.9013 | CF26: 0 | CN26: 0 | FR26: 1500 | FU26: 40.352003 | FV26: 302640.02 | FW26: 0 | FX26: 302640.02 | FY26: 0 | FZ26: 0 | GA26: -356186.72 | GB26: -22500 | GC26: 0 | GD26: -1210.5601 | GE26: -975 | GF26: -380872.28 | GG26: -50.78297 | GH26: -78232.258 | GI26: -10.430968 | GK26: HBA II
B27: 22 | C27: 46204 | D27: EBP | E27: BG. TBN | F27: BBS PLNBN (4600GAR/TS 1.5% max) Barge | G27: PLNBN BARGE JUL #03 | H27: BoCT | J27: 46220 | K27: 46220 | L27: 46220.208 | R27: 3750 | BI27: 3750 | BJ27: 7500 | BO27: 0.5 | BQ27: Plan | BU27: 33.731493 | BV27: 12.925597 | BW27: 7.3018177 | BX27: 5.6063149 | BY27: 1.3276 | BZ27: 1.1891942 | CA27: 5713.6844 | CB27: 4404.0155 | CC27: 4040.9013 | CF27: 0 | CN27: 0 | FR27: 1500 | FU27: 40.352003 | FV27: 302640.02 | FW27: 0 | FX27: 302640.02 | FY27: 0 | FZ27: 0 | GA27: -356186.72 | GB27: -22500 | GC27: 0 | GD27: -1210.5601 | GE27: -975 | GF27: -380872.28 | GG27: -50.78297 | GH27: -78232.258 | GI27: -10.430968 | GK27: HBA II
B28: 23 | C28: 46204 | D28: EBP | E28: BG. TBN | F28: BBS PLNBN (4600GAR/TS 1.5% max) Barge | G28: PLNBN BARGE JUL #04 | H28: BoCT | J28: 46222 | K28: 46222 | L28: 46222.208 | R28: 3750 | BI28: 3750 | BJ28: 7500 | BO28: 0.5 | BQ28: Plan | BU28: 33.731493 | BV28: 12.925597 | BW28: 7.3018177 | BX28: 5.6063149 | BY28: 1.3276 | BZ28: 1.1891942 | CA28: 5713.6844 | CB28: 4404.0155 | CC28: 4040.9013 | CF28: 0 | CN28: 0 | FR28: 1500 | FU28: 40.352003 | FV28: 302640.02 | FW28: 0 | FX28: 302640.02 | FY28: 0 | FZ28: 0 | GA28: -356186.72 | GB28: -22500 | GC28: 0 | GD28: -1210.5601 | GE28: -975 | GF28: -380872.28 | GG28: -50.78297 | GH28: -78232.258 | GI28: -10.430968 | GK28: HBA II
B29: 24 | C29: 46204 | D29: EBP | E29: BG. TBN | F29: BBS PLNBN (4600GAR/TS 1.5% max) Barge | G29: PLNBN BARGE JUL #05 | H29: BoCT | J29: 46224 | K29: 46224 | L29: 46224.208 | R29: 3750 | BI29: 3750 | BJ29: 7500 | BO29: 0.5 | BQ29: Plan | BU29: 33.731493 | BV29: 12.925597 | BW29: 7.3018177 | BX29: 5.6063149 | BY29: 1.3276 | BZ29: 1.1891942 | CA29: 5713.6844 | CB29: 4404.0155 | CC29: 4040.9013 | CF29: 0 | CN29: 0 | FR29: 1500 | FU29: 40.352003 | FV29: 302640.02 | FW29: 0 | FX29: 302640.02 | FY29: 0 | FZ29: 0 | GA29: -356186.72 | GB29: -22500 | GC29: 0 | GD29: -1210.5601 | GE29: -975 | GF29: -380872.28 | GG29: -50.78297 | GH29: -78232.258 | GI29: -10.430968 | GK29: HBA II
B30: 25 | C30: 46204 | D30: EBP | E30: BG. TBN | F30: BBS PLNBN (4600GAR/TS 1.5% max) Barge | G30: PLNBN BARGE JUL #06 | H30: BoCT | J30: 46226 | K30: 46226 | L30: 46226.208 | R30: 3750 | BI30: 3750 | BJ30: 7500 | BO30: 0.5 | BQ30: Plan | BU30: 33.731493 | BV30: 12.925597 | BW30: 7.3018177 | BX30: 5.6063149 | BY30: 1.3276 | BZ30: 1.1891942 | CA30: 5713.6844 | CB30: 4404.0155 | CC30: 4040.9013 | CF30: 0 | CN30: 0 | FR30: 1500 | FU30: 40.352003 | FV30: 302640.02 | FW30: 0 | FX30: 302640.02 | FY30: 0 | FZ30: 0 | GA30: -356186.72 | GB30: -22500 | GC30: 0 | GD30: -1210.5601 | GE30: -975 | GF30: -380872.28 | GG30: -50.78297 | GH30: -78232.258 | GI30: -10.430968 | GK30: HBA II
B31: 26 | C31: 46204 | D31: EBP | E31: BG. TBN | F31: BBS PLNBN (4600GAR/TS 1.5% max) Barge | G31: PLNBN BARGE JUL #07 | H31: BoCT | J31: 46228 | K31: 46228 | L31: 46228.208 | R31: 3750 | BI31: 3750 | BJ31: 7500 | BO31: 0.5 | BQ31: Plan | BU31: 33.731493 | BV31: 12.925597 | BW31: 7.3018177 | BX31: 5.6063149 | BY31: 1.3276 | BZ31: 1.1891942 | CA31: 5713.6844 | CB31: 4404.0155 | CC31: 4040.9013 | CF31: 0 | CN31: 0 | FR31: 1500 | FU31: 40.352003 | FV31: 302640.02 | FW31: 0 | FX31: 302640.02 | FY31: 0 | FZ31: 0 | GA31: -356186.72 | GB31: -22500 | GC31: 0 | GD31: -1210.5601 | GE31: -975 | GF31: -380872.28 | GG31: -50.78297 | GH31: -78232.258 | GI31: -10.430968 | GK31: HBA II
B32: 27 | C32: 46204 | D32: EBP | E32: BG. TBN | F32: BBS PLNBN (4600GAR/TS 1.5% max) Barge | G32: PLNBN BARGE JUL #08 | H32: BoCT | J32: 46230 | K32: 46230 | L32: 46230.208 | R32: 3750 | BI32: 3750 | BJ32: 7500 | BO32: 0.5 | BQ32: Plan | BU32: 33.731493 | BV32: 12.925597 | BW32: 7.3018177 | BX32: 5.6063149 | BY32: 1.3276 | BZ32: 1.1891942 | CA32: 5713.6844 | CB32: 4404.0155 | CC32: 4040.9013 | CF32: 0 | CN32: 0 | FR32: 1500 | FU32: 40.352003 | FV32: 302640.02 | FW32: 0 | FX32: 302640.02 | FY32: 0 | FZ32: 0 | GA32: -356186.72 | GB32: -22500 | GC32: 0 | GD32: -1210.5601 | GE32: -975 | GF32: -380872.28 | GG32: -50.78297 | GH32: -78232.258 | GI32: -10.430968 | GK32: HBA II
B33: 28 | C33: 46204 | D33: EBP | E33: BG. TBN | F33: BBS PLNBN (4600GAR/TS 1.5% max) Barge | G33: PLNBN BARGE JUL #09 | H33: BoCT | J33: 46232 | K33: 46232 | L33: 46232.208 | R33: 3750 | BI33: 3750 | BJ33: 7500 | BO33: 0.5 | BQ33: Plan | BU33: 33.731493 | BV33: 12.925597 | BW33: 7.3018177 | BX33: 5.6063149 | BY33: 1.3276 | BZ33: 1.1891942 | CA33: 5713.6844 | CB33: 4404.0155 | CC33: 4040.9013 | CF33: 0 | CN33: 0 | FR33: 1500 | FU33: 40.352003 | FV33: 302640.02 | FW33: 0 | FX33: 302640.02 | FY33: 0 | FZ33: 0 | GA33: -356186.72 | GB33: -22500 | GC33: 0 | GD33: -1210.5601 | GE33: -975 | GF33: -380872.28 | GG33: -50.78297 | GH33: -78232.258 | GI33: -10.430968 | GK33: HBA II
B34: 29 | C34: 46204 | D34: EBP | E34: BG. TBN | F34: BBS PLNBN (4600GAR/TS 1.5% max) Barge | G34: PLNBN BARGE JUL #10 | H34: BoCT | J34: 46234 | K34: 46234 | L34: 46234.208 | R34: 3750 | BI34: 3750 | BJ34: 7500 | BO34: 0.5 | BQ34: Plan | BU34: 33.731493 | BV34: 12.925597 | BW34: 7.3018177 | BX34: 5.6063149 | BY34: 1.3276 | BZ34: 1.1891942 | CA34: 5713.6844 | CB34: 4404.0155 | CC34: 4040.9013 | CF34: 0 | CN34: 0 | FR34: 1500 | FU34: 40.352003 | FV34: 302640.02 | FW34: 0 | FX34: 302640.02 | FY34: 0 | FZ34: 0 | GA34: -356186.72 | GB34: -22500 | GC34: 0 | GD34: -1210.5601 | GE34: -975 | GF34: -380872.28 | GG34: -50.78297 | GH34: -78232.258 | GI34: -10.430968 | GK34: HBA II
B35: 30 | C35: 46204 | D35: IMM | E35: DUMP TRUCK | F35: EUP | G35: EUP JUL #PROSPECT | H35: BoCT | J35: 46228 | K35: 46228 | L35: 46229.667 | Q35: 2000 | BJ35: 2000 | BO35: 1 | BQ35: Plan | BU35: 16.419772 | BV35: 10.419772 | BW35: 7.2325304 | BX35: 6.7481022 | BY35: 1.5779299 | BZ35: 1.4722416 | CA35: 6238.9392 | CB35: 5821.0609 | CC35: 5516.931 | CF35: 1.2934854 | CN35: 0 | FR35: 50 | FU35: 77.19 | FV35: 154380 | FW35: 2586.9708 | FX35: 156966.97 | FY35: 0 | FZ35: 0 | GA35: -115734.55 | GB35: 0 | GC35: -23346.9 | GD35: 0 | GE35: 0 | GF35: -139081.45 | GG35: -69.540724 | GH35: 17885.523 | GI35: 8.9427616 | GK35: HBA I
B36: 31 | C36: 46204 | D36: EBP | E36: MV. IRIS WAVE | F36: EPDC (1.2%) | G36: EPDC #2/6 | H36: Muara Berau | J36: 46201.104 | K36: 46201.667 | L36: 46204.419 | S36: 17528 | T36: 13772 | AB36: 15000 | AH36: 15000 | AJ36: 7500 | BJ36: 68800 | BL36: 46194 | BM36: 46203 | BO36: 0.32703488 | BQ36: In Progress | BS36: RockTree Zeus | BU36: 15.746343 | BV36: 8.9443479 | BW36: 4.4094107 | BX36: 4.0800211 | BY36: 1.1415254 | BZ36: 1.0562518 | CA36: 6654.562 | CB36: 6157.4561 | CC36: 5856.8184 | CF36: 3.9689637 | CN36: -0.014663881 | FR36: 1041.6667 | FU36: 121.392 | FV36: 8351769.6 | FW36: 273064.71 | FX36: 8624834.3 | FY36: -1008.875 | FZ36: -113128.32 | GA36: -7946510.8 | GB36: -214040.53 | GC36: 0 | GD36: -33407.078 | GE36: -8944 | GF36: -8317039.6 | GG36: -120.8872 | GH36: 307794.73 | GI36: 4.4737606 | GK36: HBA
B37: 32 | C37: 46204 | D37: EBP | E37: MV. ASTER OCEAN | F37: ZHEJIANG (5500NAR/TS 1.5%max) | G37: ZHEJIANG 5500NAR #2/5 | H37: Muara Berau | J37: 46198.5 | K37: 46202.983 | L37: 46205.843 | R37: 7500 | T37: 7500 | U37: 36200 | V37: 7500 | W37: 7500 | AW37: 5300 | BJ37: 71500 | BL37: 46198 | BM37: 46207 | BO37: 0.074125874 | BQ37: In Progress | BS37: PNTS WHS Iskandar_O | BU37: 18.03 | BV37: 11.37 | BW37: 4.92 | BX37: 4.55 | BY37: 0.96 | BZ37: 0.89 | CA37: 6331 | CB37: 5856 | CC37: 5548 | CF37: 0.51164931 | CN37: -1.3927132 | FR37: 1041.6667 | FU37: 105.32609 | FV37: 7530815.2 | FW37: 36582.926 | FX37: 7567398.1 | FY37: -99578.993 | FZ37: 0 | GA37: -7578007.3 | GB37: -263120 | GC37: 0 | GD37: -30123.261 | GE37: -9295 | GF37: -7980124.5 | GG37: -111.61013 | GH37: -412726.37 | GI37: -5.7723968 | GK37: HBA I
B38: 33 | C38: 46204 | D38: EBP | E38: MV. SILVERGATE | F38: MARUBENI (KOBE) DUMMY | G38: KOBE #02 | H38: Muara Berau | J38: 46202 | K38: 46202.958 | L38: 46205.254 | S38: 27400 | U38: 15000 | AC38: 7500 | AH38: 7500 | BJ38: 57400 | BL38: 46196 | BM38: 46205 | BO38: 0.26132404 | BQ38: In Progress | BS38: RockTree Apollo | BU38: 14.863968 | BV38: 8.6001328 | BW38: 4.4537491 | BX38: 4.1485238 | BY38: 0.69934972 | BZ38: 0.65142174 | CA38: 6720.3209 | CB38: 6259.7625 | CC38: 5949.6871 | CF38: 2.6264947 | CN38: -0.21559233 | FR38: 1041.6667 | FU38: 133.29739 | FV38: 7651270.1 | FW38: 150760.79 | FX38: 7802030.9 | FY38: -12375 | FZ38: -80285.279 | GA38: -6785701.7 | GB38: -178574.51 | GC38: 0 | GD38: -30605.08 | GE38: -7462 | GF38: -7095003.5 | GG38: -123.60633 | GH38: 707027.34 | GI38: 12.317549 | GK38: HBA
B39: 34 | C39: 46204 | D39: EBP | E39: MV. NEW HARMONY 8 | F39: SHENHUA (5200NAR/TS max 1.0%) | G39: SHENHUA 5200NAR #2/4 | H39: Muara Berau | J39: 46205 | K39: 46205.667 | L39: 46208.747 | R39: 7500 | U39: 38900 | W39: 17800 | Y39: 7500 | AV39: 5300 | BJ39: 77000 | BL39: 46200 | BM39: 46209 | BO39: 0.068831169 | BQ39: Plan | BS39: RockTree Zeus | BU39: 20.604135 | BV39: 12.455148 | BW39: 5.1511277 | BX39: 4.5637183 | BY39: 0.62813176 | BZ39: 0.57594736 | CA39: 6171.1772 | CB39: 5620.8307 | CC39: 5297.7199 | CF39: 0.41491043 | CN39: -0.043290043 | FR39: 1041.6667 | FU39: 100.71739 | FV39: 7755239.1 | FW39: 31948.103 | FX39: 7787187.2 | FY39: -3333.3333 | FZ39: 0 | GA39: -7807541.4 | GB39: -239551.17 | GC39: 0 | GD39: -31020.957 | GE39: -10010 | GF39: -8091456.9 | GG39: -105.08386 | GH39: -304269.63 | GI39: -3.9515537 | GK39: HBA I
B40: 35 | C40: 46204 | D40: EBP | E40: MV. TBN | F40: BBS PLNBN (4600GAR/TS 1.5% max) DUMMY | G40: PLNBN AUG #04 | H40: Muara Berau | J40: 46206 | K40: 46206.833 | L40: 46210.3 | U40: 22000 | Y40: 22500 | BI40: 7500 | BJ40: 52000 | BL40: 46199 | BM40: 46208 | BO40: 0.14423077 | BQ40: Plan | BS40: FC Pioneer Satu | BU40: 32.87 | BV40: 13.71 | BW40: 5.83 | BX40: 4.53 | BY40: 0.33 | BZ40: 0.26 | CA40: 5768 | CB40: 4487 | CC40: 4073 | CF40: 0 | CN40: -0.11538462 | FR40: 625 | FU40: 40.352003 | FV40: 2098304.1 | FW40: 0 | FX40: 2098304.1 | FY40: -6000 | FZ40: 0 | GA40: -2875661 | GB40: -102440 | GC40: 0 | GD40: -8393.2165 | GE40: -6760 | GF40: -2999254.2 | GG40: -57.677966 | GH40: -900950.09 | GI40: -17.325963 | GK40: HBA II
B41: 36 | C41: 46204 | D41: EBP | E41: MV. TBN | F41: HOKKAIDO ELECTRIC | G41: HOKKAIDO #02 | H41: Muara Berau | J41: 46204 | K41: 46206.009 | L41: 46209.249 | S41: 15000 | T41: 15000 | U41: 21000 | AB41: 22500 | AF41: 7500 | BJ41: 81000 | BL41: 46204 | BM41: 46213 | BO41: 0.092592593 | BQ41: Plan | BS41: PNTS WHS Iskandar_O | BU41: 13.854569 | BV41: 7.9021543 | BW41: 4.1155822 | BX41: 3.8392623 | BY41: 1.1575418 | BZ41: 1.0819953 | CA41: 6828.6614 | CB41: 6389.8772 | CC41: 6080.4546 | CF41: 3.4910429 | CN41: -0.33531366 | FR41: 1041.6667 | FU41: 127.91182 | FV41: 10360857 | FW41: 282774.48 | FX41: 10643632 | FY41: -27160.407 | FZ41: -29923.589 | GA41: -9497361.2 | GB41: -298080 | GC41: 0 | GD41: -41443.428 | GE41: -10530 | GF41: -9904498.6 | GG41: -122.27776 | GH41: 739132.97 | GI41: 9.1250984 | GK41: HBA
B42: 37 | C42: 46204 | D42: EBP | E42: MV. TBN | F42: HO PING POWER 5900 GAR (TS(max) 0.95%) | G42: HO PING POWER #3/4 | H42: Muara Berau | J42: 46206 | K42: 46208.667 | L42: 46211.467 | S42: 15000 | T42: 5000 | U42: 35000 | AH42: 15000 | BJ42: 70000 | BL42: 46206 | BM42: 46215 | BO42: 0.21428571 | BQ42: Plan | BS42: RockTree Apollo | BU42: 16.124327 | BV42: 10.377763 | BW42: 4.4570215 | BX42: 4.1666488 | BY42: 0.75902773 | BZ42: 0.70991295 | CA42: 6513.5433 | CB42: 6097.1699 | CC42: 5813.7658 | CF42: 5.91225 | CN42: -0.55714286 | FR42: 1041.6667 | FU42: 120.36672 | FV42: 8425670.4 | FW42: 413857.5 | FX42: 8839527.9 | FY42: -39000 | FZ42: -81996.591 | GA42: -7908255.7 | GB42: -217773.79 | GC42: 0 | GD42: -33702.681 | GE42: -9100 | GF42: -8289828.8 | GG42: -118.42613 | GH42: 549699.1 | GI42: 7.8528442 | GK42: HBA
B43: 38 | C43: 46204 | D43: EBP | E43: MV. SEACON NOLA | F43: JERA TRADING INC (1.3%) | G43: JERA #SPOT (TS rej 1.3%) | H43: Muara Berau | J43: 46209 | K43: 46209.915 | L43: 46212.523 | S43: 22100 | T43: 10000 | AB43: 15000 | AH43: 7500 | AL43: 5300 | AM43: 5300 | BJ43: 65200 | BL43: 46204 | BM43: 46213 | BO43: 0.27760736 | BQ43: Plan | BS43: PNTS WHS Iskandar_O | BU43: 16.148685 | BV43: 8.8251175 | BW43: 4.2873491 | BX43: 3.8994682 | BY43: 1.1100004 | BZ43: 1.0282322 | CA43: 6676.1351 | CB43: 6154.2204 | CC43: 5856.1544 | CF43: -1.191119 | CN43: -0.11444274 | FR43: 1041.6667 | FU43: 122.87817 | FV43: 8011657 | FW43: -77660.96 | FX43: 7933996 | FY43: -7461.6667 | FZ43: -94251.951 | GA43: -7456017.1 | GB43: -239936 | GC43: 0 | GD43: -32046.628 | GE43: -8476 | GF43: -7838189.3 | GG43: -120.21763 | GH43: 95806.708 | GI43: 1.469428 | GK43: HBA
B44: 39 | C44: 46204 | D44: EBP | E44: MV. RAMANAS ROSE | F44: MARUBENI (TOKUYAMA-TCM) - MCV | G44: TOKUYAMA #06 (MCV) | H44: Muara Berau | J44: 46209 | K44: 46209.667 | L44: 46210.547 | Q44: 4500 | R44: 3000 | U44: 2000 | W44: 12500 | BJ44: 22000 | BL44: 46207 | BM44: 46216 | BO44: 0 | BQ44: Plan | BS44: RockTree Zeus | BU44: 17.871206 | BV44: 12.288041 | BW44: 5.1453851 | BX44: 4.8133373 | BY44: 0.86046607 | BZ44: 0.80355621 | CA44: 6218.1902 | CB44: 5822.6845 | CC44: 5505.2148 | CF44: 1.1491043 | CN44: -0.13636364 | FR44: 1041.6667 | FU44: 134.85 | FV44: 2966700 | FW44: 25280.294 | FX44: 2991980.3 | FY44: -3000 | FZ44: 0 | GA44: -2395784.3 | GB44: -68443.191 | GC44: 0 | GD44: -11866.8 | GE44: -2860 | GF44: -2481954.3 | GG44: -112.8161 | GH44: 510026.01 | GI44: 23.183001 | GK44: HBA I
B45: 40 | C45: 46204 | D45: EBP | E45: MV. RAMANAS ROSE | F45: MARUBENI (TOKUYAMA-TCM) | G45: TOKUYAMA #06 | H45: Muara Berau | J45: 46209 | K45: 46210.667 | L45: 46212.867 | T45: 15000 | U45: 5000 | W45: 5000 | AB45: 22500 | AF45: 7500 | BJ45: 55000 | BL45: 46207 | BM45: 46216 | BO45: 0.13636364 | BQ45: Plan | BS45: RockTree Apollo | BU45: 14.16308 | BV45: 7.9775009 | BW45: 4.1550324 | BX45: 3.8606962 | BY45: 1.338725 | BZ45: 1.2492806 | CA45: 6812.2514 | CB45: 6358.1253 | CC45: 6044.7803 | CF45: 2.191119 | CN45: -0.38181818 | FR45: 1041.6667 | FU45: 134.85 | FV45: 7416750 | FW45: 120511.55 | FX45: 7537261.5 | FY45: -21000 | FZ45: -29923.589 | GA45: -6396544.1 | GB45: -171107.98 | GC45: 0 | GD45: -29667 | GE45: -7150 | GF45: -6655392.6 | GG45: -121.00714 | GH45: 881868.9 | GI45: 16.03398 | GK45: HBA
B46: 41 | C46: 46204 | D46: EBP | E46: MV. TBN | F46: TOHOKU | G46: TOHOKU #3/4 | H46: Muara Berau | J46: 46208 | K46: 46212.188 | L46: 46215.468 | S46: 36000 | T46: 9000 | U46: 7000 | W46: 7500 | AB46: 7500 | AH46: 7500 | AJ46: 7500 | BJ46: 82000 | BL46: 46208 | BM46: 46217 | BO46: 0.18292683 | BQ46: Plan | BS46: PNTS WHS Iskandar_O | BU46: 15.185338 | BV46: 8.9146958 | BW46: 4.1808885 | BX46: 3.8793297 | BY46: 0.91069894 | BZ46: 0.85083109 | CA46: 6681.2445 | CB46: 6225.8912 | CC46: 5942.616 | CF46: 2.2911872 | CN46: -0.80964308 | FR46: 1041.6667 | FU46: 128.17366 | FV46: 10510240 | FW46: 187877.35 | FX46: 10698118 | FY46: -66390.733 | FZ46: -72130.029 | GA46: -9581526.4 | GB46: -301760 | GC46: 0 | GD46: -42040.962 | GE46: -10660 | GF46: -10074508 | GG46: -122.85986 | GH46: 623609.61 | GI46: 7.6049953 | GK46: HBA
B47: 42 | C47: 46204 | D47: EBP | E47: MV. TBN | F47: ZHEJIANG (5200NAR/TS 1.0%max) | G47: ZHEJIANG 5200NAR TS 1% max #6/11 | H47: Muara Berau | J47: 46212 | K47: 46214 | L47: 46217 | U47: 40000 | V47: 9700 | W47: 5000 | AM47: 5300 | AQ47: 7500 | AT47: 7500 | BJ47: 75000 | BL47: 46212 | BM47: 46221 | BO47: 0.27066667 | BQ47: Plan | BS47: RockTree Zeus | BU47: 22.202473 | BV47: 12.53061 | BW47: 4.5573083 | BX47: 4.0252051 | BY47: 0.60451796 | BZ47: 0.55133284 | CA47: 6145.5796 | CB47: 5493.1994 | CC47: 5162.8987 | CF47: -0.31234163 | CN47: -0.36 | FR47: 1041.6667 | FU47: 100.71739 | FV47: 7553804.3 | FW47: -23425.622 | FX47: 7530378.7 | FY47: -27000 | FZ47: -56825.727 | GA47: -7314023.7 | GB47: -233329.06 | GC47: 0 | GD47: -30215.217 | GE47: -9750 | GF47: -7671143.7 | GG47: -102.28192 | GH47: -140764.96 | GI47: -1.8768662 | GK47: HBA I
B48: 43 | C48: 46204 | D48: BEK | E48: MV. TBN | F48: TENAGA NATIONAL BERHAD (6150 GAR) | G48: TNB JANAMANJUNG #BO | H48: Muara Berau | J48: 46214 | K48: 46215.667 | L48: 46217.667 | U48: 22500 | V48: 7500 | BJ48: 30000 | BL48: 46214 | BM48: 46223 | BO48: 1 | BQ48: Plan | BS48: FC Pioneer Satu | BU48: 16.327243 | BV48: 10.647278 | BW48: 4.5701103 | BX48: 4.2758158 | BY48: 0.83749959 | BZ48: 0.78001147 | CA48: 6477.1454 | CB48: 6065.8986 | CC48: 5751.5301 | CF48: 0.11362 | CN48: -0.7 | FR48: 625 | FU48: 130.46786 | FV48: 3914035.7 | FW48: 3408.6 | FX48: 3917444.3 | FY48: -21000 | FZ48: -160938.07 | GA48: -1600534.6 | GB48: -59100 | GC48: -528394.82 | GD48: 0 | GE48: 0 | GF48: -2369967.5 | GG48: -78.998916 | GH48: 1547476.8 | GI48: 51.582561 | GK48: HBA
B49: 44 | C49: 46204 | D49: EBP | E49: MV. TBN | F49: JERA TRADING INC (1.3%) | G49: JERA #3/6 (TS rej 1.3%) | H49: Muara Berau | J49: 46217 | K49: 46218.145 | L49: 46221.145 | S49: 22200 | T49: 17500 | AB49: 17200 | AJ49: 7500 | AL49: 5300 | AM49: 5300 | BJ49: 75000 | BL49: 46217 | BM49: 46226 | BO49: 0.24133333 | BQ49: Plan | BS49: RockTree Zeus | BU49: 16.042437 | BV49: 8.4581858 | BW49: 4.405971 | BX49: 3.9963214 | BY49: 1.1824314 | BZ49: 1.096078 | CA49: 6690.1559 | CB49: 6151.5894 | CC49: 5853.4024 | CF49: -1.1528345 | CN49: -0.15476958 | FR49: 1041.6667 | FU49: 118.89447 | FV49: 8917085.6 | FW49: -86462.59 | FX49: 8830623 | FY49: -11607.718 | FZ49: -84385.388 | GA49: -8520552.8 | GB49: -233329.06 | GC49: 0 | GD49: -35668.342 | GE49: -9750 | GF49: -8895293.3 | GG49: -118.60391 | GH49: -64670.31 | GI49: -0.86227079 | GK49: HBA
B50: 45 | C50: 46204 | D50: BEK | E50: MV. TBN | F50: KOWEPO (CV 5850NAR) | G50: KOWEPO JUN #SPOT | H50: Muara Berau | J50: 46217 | K50: 46220.667 | L50: 46223.867 | U50: 65000 | V50: 15000 | BJ50: 80000 | BL50: 46217 | BM50: 46226 | BO50: 1 | BQ50: Plan | BS50: PNTS WHS Iskandar_O | BU50: 16.23898 | BV50: 10.664483 | BW50: 4.5016719 | BX50: 4.2176959 | BY50: 0.76142271 | BZ50: 0.71045645 | CA50: 6484.682 | CB50: 6080.4404 | CC50: 5766.6148 | CF50: 0.103 | CN50: -0.7125 | FR50: 1041.6667 | FU50: 122.8871 | FV50: 9830967.7 | FW50: 8240 | FX50: 9839207.7 | FY50: -57000 | FZ50: -429168.18 | GA50: -4322309.4 | GB50: -216000 | GC50: -1327180.6 | GD50: 0 | GE50: 0 | GF50: -6351658.2 | GG50: -79.395727 | GH50: 3487549.5 | GI50: 43.594369 | GK50: HBA
B51: 46 | C51: 46204 | D51: EBP | E51: MV. TBN | F51: JOBAN JOINT POWER (BEK) TS max 0.75% | G51: JOBAN #2/3 | H51: Muara Berau | J51: 46219 | K51: 46221.5 | L51: 46223.9 | S51: 5000 | T51: 2500 | U51: 37500 | AC51: 7500 | AH51: 7500 | BJ51: 60000 | BL51: 46219 | BM51: 46233 | BO51: 0.25 | BQ51: Plan | BS51: RockTree Apollo | BU51: 15.879893 | BV51: 10.122416 | BW51: 4.7527492 | BX51: 4.4421307 | BY51: 0.64926638 | BZ51: 0.60741703 | CA51: 6519.4089 | CB51: 6102.6338 | CC51: 5811.7656 | CF51: 0.271538 | CN51: -0.6 | FR51: 1041.6667 | FU51: 126.38718 | FV51: 7583230.5 | FW51: 16292.28 | FX51: 7599522.8 | FY51: -36000 | FZ51: -80285.279 | GA51: -6758939.6 | GB51: -186663.25 | GC51: 0 | GD51: -30332.922 | GE51: -7800 | GF51: -7100021 | GG51: -118.33368 | GH51: 499501.76 | GI51: 8.3250294 | GK51: HBA
B52: 47 | C52: 46204 | D52: EBP | E52: MV. TBN | F52: ZHEJIANG (5500NAR/TS 1.5%max) | G52: ZHEJIANG 5500NAR #3/5 | H52: Muara Berau | J52: 46219 | K52: 46223.532 | L52: 46226.532 | R52: 7500 | T52: 7500 | U52: 22500 | V52: 15000 | W52: 15000 | AT52: 7500 | BJ52: 75000 | BL52: 46219 | BM52: 46228 | BO52: 0.1 | BQ52: Plan | BS52: PNTS WHS Iskandar_O | BU52: 18.792787 | BV52: 11.167502 | BW52: 5.0420615 | BX52: 4.5912999 | BY52: 1.0329522 | BZ52: 0.95812527 | CA52: 6314.0062 | CB52: 5785.6476 | CC52: 5465.2237 | CF52: -0.29190256 | CN52: -0.96775556 | FR52: 1041.6667 | FU52: 105.32609 | FV52: 7899456.5 | FW52: -21892.692 | FX52: 7877563.8 | FY52: -72581.667 | FZ52: 0 | GA52: -7864188.5 | GB52: -276000 | GC52: 0 | GD52: -31597.826 | GE52: -9750 | GF52: -8254118 | GG52: -110.05491 | GH52: -376554.21 | GI52: -5.0207228 | GK52: HBA I
B53: 48 | C53: 46204 | D53: EBP | E53: MV. TBN | F53: MARUBENI (KOBE) | G53: KOBE #03 | H53: Muara Berau | J53: 46220 | K53: 46224.311 | L53: 46226.711 | S53: 37500 | AC53: 15000 | AH53: 7500 | BJ53: 60000 | BL53: 46220 | BM53: 46229 | BO53: 0.375 | BQ53: Plan | BS53: RockTree Zeus | BU53: 13.656991 | BV53: 7.4899916 | BW53: 4.7126107 | BX53: 4.3877023 | BY53: 0.76548893 | BZ53: 0.71535916 | CA53: 6806.8613 | CB53: 6354.6593 | CC53: 6076.6548 | CF53: 0.8719234 | CN53: -1.1431736 | FR53: 1041.6667 | FU53: 133.29739 | FV53: 7997843.3 | FW53: 52315.404 | FX53: 8050158.7 | FY53: -68590.417 | FZ53: -119572.26 | GA53: -7299362.4 | GB53: -186663.25 | GC53: 0 | GD53: -31991.373 | GE53: -7800 | GF53: -7713979.7 | GG53: -128.56633 | GH53: 336178.95 | GI53: 5.6029825 | GK53: HBA
B54: 49 | C54: 46204 | D54: EBP | E54: MV. TBN | F54: THERMA LUZON (5700GAR/TS 0.85% max) | G54: THERMA LUZON 5700GAR TS 0.85% max #PROSPECT | H54: Muara Berau | J54: 46222 | K54: 46227.566 | L54: 46230.766 | S54: 4500 | T54: 3000 | U54: 34700 | V54: 10000 | W54: 5300 | AF54: 15000 | AQ54: 7500 | BJ54: 80000 | BL54: 46222 | BM54: 46231 | BO54: 0.28125 | BQ54: Plan | BS54: RockTree Apollo | BU54: 19.424028 | BV54: 11.802789 | BW54: 4.6767294 | BX54: 4.2728849 | BY54: 0.81254491 | BZ54: 0.7481736 | CA54: 6256.8717 | CB54: 5728.5294 | CC54: 5403.2073 | CF54: 0.41236273 | CN54: -1.1398281 | FR54: 1041.6667 | FU54: 119.89655 | FV54: 9591724.1 | FW54: 32989.019 | FX54: 9624713.2 | FY54: -91186.25 | FZ54: -91668.711 | GA54: -8222791.3 | GB54: -248884.33 | GC54: 0 | GD54: -38366.897 | GE54: -10400 | GF54: -8703297.5 | GG54: -108.79122 | GH54: 921415.62 | GI54: 11.517695 | GK54: HBA I
B55: 50 | C55: 46204 | D55: EBP | E55: MV. TBN | F55: EPDC (1.2%) | G55: EPDC #3/6 | H55: Muara Berau | J55: 46223 | K55: 46230.917 | L55: 46233.917 | S55: 7500 | T55: 15000 | U55: 17200 | AB55: 15000 | AH55: 7500 | AJ55: 7500 | AL55: 5300 | BJ55: 75000 | BL55: 46223 | BM55: 46232 | BO55: 0.27066667 | BQ55: Plan | BS55: RockTree Zeus | BU55: 16.202432 | BV55: 9.4477795 | BW55: 4.5046039 | BX55: 4.1458348 | BY55: 1.0548961 | BZ55: 0.98208152 | CA55: 6588.8283 | CB55: 6104.6924 | CC55: 5819.503 | CF55: 3.79303 | CN55: -1.78 | FR55: 1041.6667 | FU55: 121.392 | FV55: 9104400 | FW55: 284477.25 | FX55: 9388877.2 | FY55: -133500 | FZ55: -100379.49 | GA55: -8419813.4 | GB55: -233329.06 | GC55: 0 | GD55: -36417.6 | GE55: -9750 | GF55: -8933189.5 | GG55: -119.10919 | GH55: 455687.74 | GI55: 6.0758365 | GK55: HBA
B56: 51 | C56: 46204 | D56: TCM | E56: BG. TBN | F56: INDOCEMENT (2024) | G56: INDOCEMENT TCM #04 | H56: Bunyut | J56: 46224 | K56: 46224.042 | L56: 46224.342 | S56: 3272.28 | T56: 4227.72 | BJ56: 7500 | BO56: 1 | BQ56: Plan | BU56: 12.127387 | BV56: 6.3512632 | BW56: 4.8057913 | BX56: 4.5082383 | BY56: 1.5500006 | BZ56: 1.4536929 | CA56: 6929.001 | CB56: 6501.7316 | CC56: 6198.2055 | CF56: 0 | CN56: 0 | FR56: 1041.6667 | FU56: 80.65 | FV56: 604875 | FW56: 0 | FX56: 604875 | FY56: 0 | FZ56: 0 | GA56: -513972.36 | GB56: 0 | GC56: -124405.88 | GD56: 0 | GE56: 0 | GF56: -638378.23 | GG56: -85.117098 | GH56: -33503.234 | GI56: -4.4670979 | GK56: HBA
GH57: 3204491.4
L58: Total Coal Loading of BoCT | N58: 24591.47 | O58: 0 | P58: 0 | Q58: 18000 | R58: 576193.05 | S58: 34500 | T58: 3000 | U58: 82500 | V58: 45000 | W58: 0 | X58: 0 | Y58: 135000 | Z58: 0 | AA58: 0 | AB58: 30000 | AC58: 0 | AD58: 0 | AE58: 0 | AF58: 0 | AG58: 0 | AH58: 22508.53 | AI58: 0 | AJ58: 7500 | AK58: 0 | AL58: 5300 | AM58: 0 | AN58: 0 | AO58: 0 | AP58: 0 | AQ58: 15000 | AR58: 0 | AS58: 5300 | AT58: 30000 | AU58: 0 | AV58: 10600 | AW58: 0 | AX58: 20204.95 | AY58: 0 | AZ58: 0 | BA58: 0 | BB58: 0 | BC58: 0 | BD58: 0 | BE58: 0 | BF58: 0 | BG58: 0 | BH58: 0 | BI58: 165002 | BJ58: 1230200 | CF58: -0.038234657 | CN58: -0.5879528 | FR58: 1800
L59: Total Coal Loading of Mahakam | N59: 0 | O59: 0 | P59: 0 | Q59: 4500 | R59: 25500 | S59: 213000.28 | T59: 124999.72 | U59: 421500 | V59: 64700 | W59: 75600 | X59: 0 | Y59: 30000 | Z59: 0 | AA59: 0 | AB59: 114700 | AC59: 30000 | AD59: 0 | AE59: 0 | AF59: 30000 | AG59: 0 | AH59: 75000 | AI59: 0 | AJ59: 30000 | AK59: 0 | AL59: 15900 | AM59: 15900 | AN59: 0 | AO59: 0 | AP59: 0 | AQ59: 15000 | AR59: 0 | AS59: 0 | AT59: 15000 | AU59: 0 | AV59: 5300 | AW59: 5300 | AX59: 0 | AY59: 0 | AZ59: 0 | BA59: 0 | BB59: 0 | BC59: 0 | BD59: 0 | BE59: 0 | BF59: 0 | BG59: 0 | BH59: 0 | BI59: 7500 | BJ59: 1319400 | CF59: 0.53216468 | CN59: -0.60995533 | FR59: 1001.9841
J60: Total Coal Loading of ITM (Coal Demand) | N60: 24591.47 | O60: 0 | P60: 0 | Q60: 22500 | R60: 601693.05 | S60: 247500.28 | T60: 127999.72 | U60: 504000 | V60: 109700 | W60: 75600 | X60: 0 | Y60: 165000 | Z60: 0 | AA60: 0 | AB60: 144700 | AC60: 30000 | AD60: 0 | AE60: 0 | AF60: 30000 | AG60: 0 | AH60: 97508.53 | AI60: 0 | AJ60: 37500 | AK60: 0 | AL60: 21200 | AM60: 15900 | AN60: 0 | AO60: 0 | AP60: 0 | AQ60: 30000 | AR60: 0 | AS60: 5300 | AT60: 45000 | AU60: 0 | AV60: 15900 | AW60: 5300 | AX60: 20204.95 | AY60: 0 | AZ60: 0 | BA60: 0 | BB60: 0 | BC60: 0 | BD60: 0 | BE60: 0 | BF60: 0 | BG60: 0 | BH60: 0 | BI60: 172502 | BJ60: 2549600 | BK60: 0 | CF60: 0.25694297 | CN60: -0.59933895
L62: Inventory | CF62: 0.52726489
L63: Total BOP (Beginning of Period) | N63: 31590.25 | O63: 1531.95 | P63: 0 | Q63: 38585.955 | R63: 248951.62 | S63: 141221.88 | T63: 137430.57 | U63: 155122.72 | V63: 25281.874 | W63: 25000 | X63: 1370.339 | Y63: 79934.329 | Z63: 0 | AA63: 0 | AB63: 88705.094 | AC63: 7500 | AD63: 0 | AE63: 0 | AF63: 0 | AG63: 0 | AH63: 45000 | AI63: 0 | AJ63: 15000 | AK63: 0 | AL63: 10600 | AM63: 10600 | AN63: 0 | AO63: 0 | AP63: 0 | AQ63: 0 | AR63: 0 | AS63: 5300 | AT63: 29999.93 | AU63: 0 | AV63: 5300 | AW63: 5300.37 | AX63: 15000.05 | AY63: 0 | AZ63: 0 | BA63: 0 | BB63: 0 | BC63: 0 | BD63: 0 | BE63: 0 | BF63: 0 | BG63: 0 | BH63: 0 | BI63: 22500 | BJ63: 1146826.9 | CF63: 1.389235
L64: PSY at Barge Port (Bunyut and JBG) | BJ64: 0
L65: PSY at Vessel Port (BoCT) | BJ65: 0
L66: Coal on Water/Intransit (Barge,Vessel, Storage) | BJ66: 0
L67: Monthly FC Production Plan | N67: 30628.429 | O67: 0 | P67: 0 | Q67: 0.19880685 | R67: 583639.37 | S67: 150000 | T67: 63000 | U67: 480000 | V67: 150000 | W67: 70000 | X67: 0 | Y67: 160000 | Z67: 0 | AA67: 0 | AB67: 70000 | AC67: 30000 | AD67: 0 | AE67: 0 | AF67: 30000 | AG67: 0 | AH67: 60000 | AI67: 0 | AJ67: 22500 | AK67: 0 | AL67: 15900 | AM67: 15900 | AN67: 0 | AO67: 0 | AP67: 0 | AQ67: 30000 | AR67: 0 | AS67: 5300 | AT67: 45000 | AU67: 0 | AV67: 15900 | AW67: 10600 | AX67: 15000 | AY67: 0 | AZ67: 0 | BA67: 0 | BB67: 0 | BC67: 0 | BD67: 0 | BE67: 0 | BF67: 0 | BG67: 0 | BH67: 0 | BI67: 150000 | BJ67: 2203368
L68: Update Coal Flow as ….. (Based on Report ….)
L69: PSY at Barge Port (Bunyut and JBG) | BJ69: 0
L70: PSY at Vessel Port (BoCT) | BJ70: 0
L71: Coal on Water/Intransit (Barge,Vessel, Storage) | BJ71: 0
L72: Cargo already completed on vessel during period | BJ72: 0
L73: Actual Crushing During Period | BJ73: 0
L74: Outlook FC Production (remain crushing) | N74: 30628.429 | O74: 0 | P74: 0 | Q74: 0.19880685 | R74: 583639.37 | S74: 150000 | T74: 63000 | U74: 480000 | V74: 150000 | W74: 70000 | X74: 0 | Y74: 160000 | Z74: 0 | AA74: 0 | AB74: 70000 | AC74: 30000 | AD74: 0 | AE74: 0 | AF74: 30000 | AG74: 0 | AH74: 60000 | AI74: 0 | AJ74: 22500 | AK74: 0 | AL74: 15900 | AM74: 15900 | AN74: 0 | AO74: 0 | AP74: 0 | AQ74: 30000 | AR74: 0 | AS74: 5300 | AT74: 45000 | AU74: 0 | AV74: 15900 | AW74: 10600 | AX74: 15000 | AY74: 0 | AZ74: 0 | BA74: 0 | BB74: 0 | BC74: 0 | BD74: 0 | BE74: 0 | BF74: 0 | BG74: 0 | BH74: 0 | BI74: 150000 | BJ74: 2203368
L75: Coal Supply Chain
L76: Prediction Ending Inventory | N76: 37627.209 | O76: 1531.95 | P76: 0 | Q76: 16086.154 | R76: 230897.94 | S76: 43721.598 | T76: 72430.846 | U76: 131122.72 | V76: 65581.874 | W76: 19400 | X76: 1370.339 | Y76: 74934.329 | Z76: 0 | AA76: 0 | AB76: 14005.094 | AC76: 7500 | AD76: 0 | AE76: 0 | AF76: 0 | AG76: 0 | AH76: 7500.47 | AI76: 0 | AJ76: 0 | AK76: 0 | AL76: 5300 | AM76: 10600 | AN76: 0 | AO76: 0 | AP76: 0 | AQ76: 0 | AR76: 0 | AS76: 5300 | AT76: 29999.93 | AU76: 0 | AV76: 5300 | AW76: 10600.37 | AX76: 10000.1 | AY76: 0 | AZ76: 0 | BA76: 0 | BB76: 0 | BC76: 0 | BD76: 0 | BE76: 0 | BF76: 0 | BG76: 0 | BH76: 0 | BI76: 0 | BJ76: 800810.93

Sheet Summary_Actual
A1: Summary Loading of ITM Shipment 2023
A2: Calculation Sheet
B3: Jul
B4: Shipment | J4: ETA/ATA, ETB, and ETD | N4: IMM | O4: IMM | P4: IMM | Q4: IMM | R4: IMM | S4: TCM | T4: TCM | U4: BEK | V4: BEK | W4: BEK | X4: JBG | Y4: GPK | Z4: NPR | AA4: NPR | AB4: TIS | AC4: EBP | AD4: EBP | AE4: EBP | AF4: EBP | AG4: EBP | AH4: EBP | AI4: EBP | AJ4: EBP | AK4: EBP | AL4: EBP | AM4: EBP | AN4: EBP | AO4: EBP | AP4: EBP | AQ4: EBP | AR4: EBP | AS4: EBP | AT4: EBP | AU4: EBP | AV4: EBP | AW4: EBP | AX4: EBP | AY4: EBP | AZ4: EBP | BA4: EBP | BB4: EBP | BC4: EBP | BD4: EBP | BE4: EBP | BF4: EBP | BG4: EBP | BH4: EBP | BI4: EBP | BJ4: Total | BL4: Laycan | BO4: Shipper | BQ4: Status | BS4: Name | BU4: Result: Coal quality by property | CF4: Penalty | CN4: Demurrage | CV4: Shipment | CX4: Value Coal Blended (FOB) | DF4: FOB | DG4: FOB | DH4: FOB | DI4: FOB | DJ4: FOB | DK4: FOB | DL4: FOB | DM4: FOB | DN4: FOB | DO4: FOB | DP4: FOB | DQ4: FOB | DR4: FOB | DS4: FOB | DT4: FOB | DU4: FOB | DV4: FOB | DW4: FOB | DX4: FOB | DY4: FOB | DZ4: FOB | EA4: FOB | EB4: FOB | EC4: FOB | ED4: FOB | EE4: FOB | EF4: FOB | EH4: FOB | EI4: FOB | EJ4: FOB | EK4: FOB | EL4: FOB | EM4: FOB | EN4: FOB | EO4: FOB | EP4: FOB | EQ4: FOB | ER4: FOB | ES4: FOB | ET4: FOB | EU4: FOB | EV4: FOB | EW4: FOB | EX4: FOB | EY4: FOB | EZ4: FOB | FA4: FOB | FB4: FOB | FC4: FOB | FD4: FOB | FE4: FOB | FF4: FOB | FG4: FOB | FH4: FOB | FJ4: Cost to Vessel (Operation) | FR4: GLR | FU4: FOB Price | FV4: Shipment Price | FW4: Bonus/Penalty | FX4: Revenue | FY4: Demurrage | FZ4: Barging Cost | GA4: Cash Cost to Vessel | GB4: FLF Cost | GC4: Royalty | GD4: Agency | GE4: Surveyor | GF4: Total Cost | GG4: Total Cost | GH4: Margin | GI4: Margin | GK4: HBA
B5: No. | C5: Month | D5: Company | E5: Name of Vessel | F5: Buyer | G5: End user | H5: Load Port | J5: ETA/ATA | K5: ETB | L5: ETD | N5: IMM-WB.HCV.LS | O5: IMM-WB.HCV.HS | P5: IMM-EB.MCV.LS | Q5: IMM-EB.MCV.MS | R5: IMM-EB.MCV.HS | S5: TCM.HCV.LS | T5: TCM.HCV.HS | U5: BEK.HCV.LS | V5: BEK.HCV.HS | W5: BEK.MCV.LS | X5: JBG | Y5: GPK | Z5: NPR.MCV.LS | AA5: NPR.MCV.HS | AB5: TIS | AC5: EBH.HCV | AD5: SHORE.HCV | AE5: KMIA.MCV.LS | AF5: BBE.MCV | AG5: MBL.MCV | AH5: MBL.56.MCV | AI5: GHP.MCV | AJ5: EMJ.MCV | AK5: EMJ.MCV | AL5: KBM.MCV | AM5: IKJ.MCV | AN5: PUMA MCV | AO5: AUB | AP5: MKE.LCV | AQ5: KJA.LCV.LS | AR5: JHN.LCV | AS5: DMP.LCV | AT5: MCM.LCV | AU5: EBH.LCV | AV5: GIE.LCV | AW5: HWA.LCV | AX5: BBA.LCV | AY5: MML.LCV | AZ5: NEI.LCV | BA5: DJA.LCV | BB5: GAM.LCV | BC5: KJM.LCV | BD5: DBP.LCV | BE5: DMP | BF5: BBS 34 | BG5: BUM.LCV | BH5: IWBM.LCV | BI5: BISM.LCV | BJ5: Total | BL5: Lay | BM5: can | BO5: % | BQ5: Status | BS5: FLF | BU5: TM (AR) | BV5: M (AD) | BW5: ASH (AD) | BX5: ASH (AR) | BY5: TS (AD) | BZ5: TS (AR) | CA5: CV (AD) | CB5: CV (AR) | CC5: CV (NAR) | CF5: W5 | CG5: W1 | CH5: W2 | CI5: W3 | CJ5: W4 | CK5: W5 | CL5: Act | CN5: W5 | CO5: W1 | CP5: W2 | CQ5: W3 | CR5: W4 | CS5: W5 | CT5: Act | CV5: Price ($) | CX5: W0 | CY5: W1 | CZ5: W2 | DA5: W3 | DB5: W4 | DC5: W5 | DD5: Act | DF5: IMM WB HCV LS | DG5: IMM WB HCV HS | DH5: IMM EB MCV LS | DI5: IMM EB MCV MS | DJ5: IMM EB MCV HS | DK5: IMMEAST SupHS | DL5: TCM HCV LS | DM5: TCM HCV HS | DN5: TCM HCV MS | DO5: BEK MCV LS | DP5: BEK MCV MS | DQ5: EMB | DR5: JBG | DS5: IKJ | DT5: BBA | DU5: IDX | DV5: KMIA | DW5: BBE | DX5: BP | DY5: KEI | DZ5: KJA | EA5: KBM | EB5: ALH | EC5: DUM | ED5: JHN | EE5: LSP | EF5: PIDI | EH5: IMM WB HCV LS | EI5: IMM WB HCV HS | EJ5: IMM EB MCV LS | EK5: IMM EB MCV MS | EL5: IMM EB MCV HS | EM5: IMMEAST SupHS | EN5: TCM HCV LS | EO5: TCM HCV HS | EP5: TCM HCV MS | EQ5: BEK MCV LS | ER5: BEK MCV MS | ES5: EMB | ET5: JBG | EU5: IKJ | EV5: BBA | EW5: IDX | EX5: KMIA | EY5: BBE | EZ5: BP | FA5: KEI | FB5: KJA | FC5: KBM | FD5: ALH | FE5: DUM | FF5: JHN | FG5: LSP | FH5: PIDI | FJ5: W0 | FK5: W1 | FL5: W2 | FM5: W3 | FN5: W4 | FO5: W5 | FP5: Act | FR5: TPH | FU5: $/ton | FV5: $ | FW5: $ | FX5: $ | FY5: $ | FZ5: $ | GA5: $ | GB5: $ | GC5: $ | GD5: $ | GE5: $ | GF5: $ | GG5: $/ton | GH5: $ | GI5: $/ton | GK5: Class
B6: 1 | C6: 46204 | D6: EBP | E6: MV. HABCO VELA | F6: BBS PLNBN (4600GAR/TS 1.5% max) | G6: PLNBN JUN #06 | H6: BoCT | J6: 46202.25 | K6: 46203.142 | L6: 46204.852 | R6: 25091.86 | AT6: 7553.14 | BI6: 22355 | BJ6: 55000 | BL6: 46200 | BM6: 46209 | BO6: 0.54378436 | BQ6: Completed | BU6: 32.98 | BV6: 14.45 | BW6: 5.54 | BX6: 4.34 | BY6: 1.14 | BZ6: 0.89 | CA6: 5661 | CB6: 4435 | CC6: 4078 | CF6: 0 | CN6: 0 | FR6: 1340.3737 | FU6: 41.17 | FV6: 2264350 | FW6: 0 | FX6: 2264350 | FY6: 0 | FZ6: 0 | GA6: -2759078.4 | GB6: -165000 | GC6: 0 | GD6: -9057.4 | GE6: -7150 | GF6: -2940285.8 | GG6: -53.459741 | GH6: -675935.76 | GI6: -12.289741 | GK6: HBA II
B7: 2 | C7: 46204 | D7: EBP | E7: MV. VINCA | F7: MARUBENI-TOSOH (JFY2024) | G7: TOSOH #03 | H7: BoCT | J7: 46193.312 | K7: 46205.049 | L7: 46205.828 | N7: 4413.95 | R7: 1557.58 | S7: 4517.39 | T7: 3011.6 | U7: 15724.81 | AB7: 7466.14 | AH7: 7508.53 | BJ7: 44200 | BL7: 46192 | BM7: 46201 | BO7: 0.16987624 | BQ7: Completed | BU7: 15.68 | BV7: 9.63 | BW7: 4.14 | BX7: 3.86 | BY7: 0.91 | BZ7: 0.84 | CA7: 6646 | CB7: 6201 | CC7: 5901 | CF7: -1.46 | CN7: -4.0084441 | FR7: 2361.5316 | FU7: 142.02 | FV7: 6277284 | FW7: -64532 | FX7: 6212752 | FY7: -177173.23 | FZ7: -41044.924 | GA7: -5078471.7 | GB7: -132600 | GC7: 0 | GD7: -25109.136 | GE7: -5746 | GF7: -5460145 | GG7: -123.53269 | GH7: 752606.99 | GI7: 17.027308 | GK7: HBA
B8: 3 | C8: 46204 | D8: EBP | E8: MV. KM SINGAPORE | F8: CHINA BAI GUI (XINDIAN 2022- 5200NAR/TS rej 2.2%) | G8: XINDIAN BAI GUI 5200NAR #10/19 | H8: BoCT | J8: 46204.479 | K8: 46205.995 | L8: 46207.419 | R8: 64292.38 | Y8: 7502.67 | AX8: 5204.95 | BJ8: 77000 | BL8: 46196 | BM8: 46205 | BO8: 0.067596753 | BQ8: Completed | BU8: 20.1 | BV8: 12.38 | BW8: 6.4 | BX8: 5.83 | BY8: 2.02 | BZ8: 1.84 | CA8: 5995 | CB8: 5467 | CC8: 5152 | CF8: -2.59 | CN8: 0.073728355 | FR8: 2252.5597 | FU8: 96.06 | FV8: 7396620 | FW8: -199430 | FX8: 7197190 | FY8: 5677.0833 | FZ8: 0 | GA8: -7314612.5 | GB8: -231000 | GC8: 0 | GD8: -29586.48 | GE8: -10010 | GF8: -7579531.9 | GG8: -98.43548 | GH8: -382341.93 | GI8: -4.9654796 | GK8: HBA I
B9: 4 | C9: 46204 | D9: EBP | E9: MV. KENCANA BARUNA | F9: TJ JATI IMM (2025 NEW) | G9: TJ JATI IMM JUL #1 | H9: BoCT | J9: 46205.387 | K9: 46207.588 | L9: 46208.812 | R9: 52013.92 | Y9: 15002.08 | BJ9: 67016 | BL9: 46206 | BM9: 46215 | BO9: 0 | BQ9: Completed | BU9: 20.73 | BV9: 13.75 | BW9: 6.96 | BX9: 6.39 | BY9: 1.92 | BZ9: 1.77 | CA9: 5840 | CB9: 5367 | CC9: 5050 | CF9: 0 | CN9: -0.020760455 | FR9: 2280.7487 | FU9: 52.36 | FV9: 3508957.8 | FW9: 0 | FX9: 3508957.8 | FY9: -1391.2827 | FZ9: 0 | GA9: -3580709.4 | GB9: -201048 | GC9: 0 | GD9: -14035.831 | GE9: -8712.08 | GF9: -3805896.6 | GG9: -56.790865 | GH9: -296938.84 | GI9: -4.4308649 | GK9: HBA I
B10: 5 | C10: 46204 | D10: IMM | E10: MV. XIN HAI TONG 810 | F10: TENAGA NATIONAL BERHAD (5523 GAR) | G10: TNB JIMAH #3/6 | H10: BoCT | J10: 46206.583 | K10: 46208.99 | L10: 46210.861 | N10: 13052.08 | Q10: 11049.08 | R10: 54598.84 | BJ10: 78700 | BL10: 46198 | BM10: 46207 | BO10: 1 | BQ10: Completed | BU10: 14.92 | BV10: 11.14 | BW10: 5.76 | BX10: 5.52 | BY10: 1.95 | BZ10: 1.87 | CA10: 6262 | CB10: 5995 | CC10: 5697 | CF10: 4.96 | CN10: -0.28090498 | FR10: 1752.1336 | FU10: 95.33 | FV10: 7502471 | FW10: 390352 | FX10: 7892823 | FY10: -22107.222 | FZ10: 0 | GA10: -4763009.8 | GB10: 0 | GC10: -1012833.6 | GD10: 0 | GE10: 0 | GF10: -5797950.6 | GG10: -73.671545 | GH10: 2094872.4 | GI10: 26.618455 | GK10: HBA I
B11: 6 | C11: 46204 | D11: EBP | E11: MV. VIET THUAN 80-06 | F11: CHINA BAI GUI (XINDIAN 2022- 5200NAR/TS rej 2.2%) | G11: XINDIAN BAI GUI 5200NAR #11/19 | H11: BoCT | J11: 46206.833 | K11: 46211.045 | L11: 46212.309 | R11: 60974.81 | AT11: 7615.2 | AX11: 5009.99 | BJ11: 73600 | BL11: 46208 | BM11: 46217 | BO11: 0.17153791 | BQ11: Completed | BU11: 19.71 | BV11: 11.78 | BW11: 6.22 | BX11: 5.66 | BY11: 2.01 | BZ11: 1.83 | CA11: 6031 | CB11: 5489 | CC11: 5176 | CF11: -2.31 | CN11: -0.48138587 | FR11: 2426.3736 | FU11: 95.37 | FV11: 7019232 | FW11: -170016 | FX11: 6849216 | FY11: -35430 | FZ11: 0 | GA11: -7053573.3 | GB11: -220800 | GC11: 0 | GD11: -28076.928 | GE11: -9568 | GF11: -7347448.2 | GG11: -99.82946 | GH11: -498232.23 | GI11: -6.7694597 | GK11: HBA I
B12: 7 | C12: 46204 | D12: EBP | E12: MV. LUMOSO KARUNIA VIII | F12: BBS PLNBN (4600GAR/TS 1.5% max) | G12: PLNBN JUL #01 | H12: BoCT | J12: 46209.896 | K12: 46214.917 | L12: 46216.378 | R12: 7055.96 | U12: 7389.3 | V12: 7538.9 | Y12: 15002.84 | BI12: 15013 | BJ12: 52000 | BL12: 46209 | BM12: 46215 | BO12: 0.28871154 | BQ12: Completed | BU12: 32.43 | BV12: 16.85 | BW12: 5.83 | BX12: 4.74 | BY12: 0.85 | BZ12: 0.69 | CA12: 5558 | CB12: 4517 | CC12: 4177.8079 | CF12: 0 | CN12: 0 | FR12: 1482.1853 | FU12: 41.17 | FV12: 2140840 | FW12: 0 | FX12: 2140840 | FY12: 0 | FZ12: 0 | GA12: -2665501.3 | GB12: -156000 | GC12: 0 | GD12: -8563.36 | GE12: -6760 | GF12: -2836824.7 | GG12: -54.554321 | GH12: -695984.68 | GI12: -13.384321 | GK12: HBA II
B13: 8 | C13: 46204 | D13: EBP | E13: MV. SINCERE SMART | F13: SHENHUA (5200NAR/TS max 2.0%) | G13: SHENHUA 5200NAR TS 2% #4/6 | H13: BoCT | J13: 46211.404 | K13: 46216.544 | L13: 46217.972 | Q13: 4993.54 | R13: 39911.3 | U13: 7477.16 | AQ13: 7507 | AV13: 5110 | BJ13: 64999 | BL13: 46213 | BM13: 46222 | BO13: 0.19411068 | BQ13: Completed | BU13: 19.22 | BV13: 11.8 | BW13: 6.32 | BX13: 5.79 | BY13: 1.86 | BZ13: 1.7 | CA13: 6034 | CB13: 5527 | CC13: 5215 | CF13: 0.46 | CN13: -0.088080201 | FR13: 1896.858 | FU13: 95.35 | FV13: 6197654.6 | FW13: 29899.54 | FX13: 6227554.2 | FY13: -5725.125 | FZ13: -31851.233 | GA13: -6322616.5 | GB13: -194997 | GC13: 0 | GD13: -24790.619 | GE13: -8449.87 | GF13: -6588430.3 | GG13: -101.36203 | GH13: -360876.16 | GI13: -5.5520263 | GK13: HBA I
B14: 9 | C14: 46204 | D14: EBP | E14: MV. LUMOSO PRATAMA | F14: TJ JATI IMM (2025 NEW) | G14: TJ JATI IMM JUL #2 | H14: BoCT | J14: 46214.508 | K14: 46218.567 | L14: 46219.803 | R14: 52003.29 | Y14: 15003.71 | BJ14: 67007 | BL14: 46216 | BM14: 46225 | BO14: 0 | BQ14: Completed | BU14: 20.66 | BV14: 13.49 | BW14: 7.04 | BX14: 6.46 | BY14: 1.98 | BZ14: 1.81 | CA14: 5841 | CB14: 5357 | CC14: 5041 | CF14: 0 | CN14: -0.24458646 | FR14: 2257.3947 | FU14: 51.52 | FV14: 3452200.6 | FW14: 0 | FX14: 3452200.6 | FY14: -16389.005 | FZ14: 0 | GA14: -3580228.7 | GB14: -201021 | GC14: 0 | GD14: -13808.803 | GE14: -8710.91 | GF14: -3820158.4 | GG14: -57.011333 | GH14: -367957.73 | GI14: -5.4913327 | GK14: HBA I
B15: 10 | C15: 46204 | D15: EBP | E15: MV. KARTINI BARUNA | F15: TJ JATI IMM (2025 NEW) | G15: TJ JATI IMM JUL #3 | H15: BoCT | J15: 46219.917 | K15: 46220.031 | L15: 46221.333 | R15: 52020.98 | Y15: 15002.02 | BJ15: 67023 | BL15: 46220 | BM15: 46229 | BO15: 0 | BQ15: Completed | BU15: 20.3 | BV15: 13.29 | BW15: 6.49 | BX15: 5.97 | BY15: 1.99 | BZ15: 1.82 | CA15: 5891 | CB15: 5384 | CC15: 5098 | CF15: 0 | CN15: 0.10369599 | FR15: 2143.5928 | FU15: 51.87 | FV15: 3476483 | FW15: 0 | FX15: 3476483 | FY15: 6950.0162 | FZ15: 0 | GA15: -3581083.4 | GB15: -201069 | GC15: 0 | GD15: -13905.932 | GE15: -8712.99 | GF15: -3797821.3 | GG15: -56.664448 | GH15: -321338.26 | GI15: -4.7944476 | GK15: HBA I
B16: 11 | C16: 46204 | D16: EBP | E16: MV. JIN NING 7 | F16: CHINA BAI GUI (XINDIAN) - 4450NAR/TS(max) 1.7% | G16: XINDIAN BAI GUI #3/7 (4450NAR) | H16: BoCT | J16: 46220.546 | K16: 46221.912 | L16: 46223.415 | R16: 35521.89 | Y16: 15003.14 | AQ16: 7515 | AX16: 5009.97 | BJ16: 63050 | BL16: 46218 | BM16: 46227 | BO16: 0.19865139 | BQ16: Completed | BU16: 26.22 | BV16: 14.95 | BW16: 6.48 | BX16: 5.62 | BY16: 1.49 | BZ16: 1.29 | CA16: 5591 | CB16: 4850 | CC16: 4516 | CF16: -0.86 | CN16: -0.23460657 | FR16: 1748.1516 | FU16: 77.82 | FV16: 4906551 | FW16: -54223 | FX16: 4852328 | FY16: -14791.944 | FZ16: -31885.176 | GA16: -5190288.5 | GB16: -189150 | GC16: 0 | GD16: -19626.204 | GE16: -8196.5 | GF16: -5453938.4 | GG16: -86.501798 | GH16: -601610.36 | GI16: -9.541798 | GK16: HBA II
B17: 12 | C17: 46204 | D17: EBP | E17: MV. ARIMBI BARUNA | F17: TJ JATI IMM (2025 NEW) | G17: TJ JATI IMM JUL #4 | H17: BoCT | J17: 46223.271 | K17: 46223.842 | L17: 46225.03 | R17: 52002.62 | Y17: 15003.38 | BJ17: 67006 | BL17: 46225 | BM17: 46234 | BO17: 0 | BQ17: Completed | BU17: 20.58 | BV17: 13.32 | BW17: 6.82 | BX17: 6.24 | BY17: 1.91 | BZ17: 1.75 | CA17: 5872 | CB17: 5375 | CC17: 5059 | CF17: 0 | CN17: 0.11818292 | FR17: 2349.7136 | FU17: 51.82 | FV17: 3472250.9 | FW17: 0 | FX17: 3472250.9 | FY17: 7918.9648 | FZ17: 0 | GA17: -3580175.2 | GB17: -201018 | GC17: 0 | GD17: -13889.004 | GE17: -8710.78 | GF17: -3795874 | GG17: -56.649763 | GH17: -323623.12 | GI17: -4.8297633 | GK17: HBA I
B18: 13 | C18: 46204 | D18: EBP | E18: MV. BULK BATAVIA | F18: TJ JATI IMM (2025 NEW) | G18: TJ JATI IMM AUG #1 | H18: BoCT | J18: 46224.721 | K18: 46225.185 | L18: 46226.448 | R18: 52018.51 | Y18: 15001.49 | BJ18: 67020 | BL18: 46226 | BM18: 46235 | BO18: 0 | BQ18: Completed | BU18: 20.58 | BV18: 13.23 | BW18: 6.82 | BX18: 6.24 | BY18: 1.91 | BZ18: 1.75 | CA18: 5872 | CB18: 5376 | CC18: 5059 | CF18: 0 | CN18: 0.10855604 | FR18: 2210.6652 | FU18: 52.87 | FV18: 3543347.4 | FW18: 0 | FX18: 3543347.4 | FY18: 7275.426 | FZ18: 0 | GA18: -3580923.1 | GB18: -201060 | GC18: 0 | GD18: -14173.39 | GE18: -8712.6 | GF18: -3797593.6 | GG18: -56.663588 | GH18: -254246.24 | GI18: -3.7935876 | GK18: HBA I
B19: 14 | C19: 46204 | D19: EBP | E19: MV. MU XI | F19: SUNNY EXPRESS (5,200NAR/ TS(rej) 2.2%) | G19: SUNNY EXPRESS #7/12 | H19: BoCT | J19: 46226.75 | K19: 46226.885 | L19: 46228.184 | Q19: 14872.56 | R19: 39897.45 | AV19: 5130 | AX19: 5099.99 | BJ19: 65000 | BL19: 46222 | BM19: 46231 | BO19: 0.15738446 | BQ19: Completed | BU19: 19.57 | BV19: 11.52 | BW19: 6.51 | BX19: 5.92 | BY19: 1.79 | BZ19: 1.63 | CA19: 6045 | CB19: 5495 | CC19: 5182 | CF19: -2.16 | CN19: 0.050213675 | FR19: 2085.5615 | FU19: 93.97 | FV19: 6108050 | FW19: -140400 | FX19: 5967650 | FY19: 3263.8889 | FZ19: 0 | GA19: -6297081.6 | GB19: -195000 | GC19: 0 | GD19: -24432.2 | GE19: -8450 | GF19: -6521699.9 | GG19: -100.33384 | GH19: -554049.87 | GI19: -8.5238441 | GK19: HBA I
B20: 15 | C20: 46204 | D20: EBP | E20: MV. LUMOSO KARUNIA VIII | F20: BBS PLNBN (4600GAR/TS 1.5% max) | G20: PLNBN JUL #02 | H20: BoCT | J20: 46230.34 | K20: 46230.464 | L20: 46231.922 | R20: 6942.74 | U20: 7652.19 | V20: 7401.64 | Y20: 15002.43 | BI20: 15001 | BJ20: 52000 | BL20: 46215 | BM20: 46221 | BO20: 0.28848077 | BQ20: Completed | BU20: 32.79 | BV20: 14.79 | BW20: 5.71 | BX20: 4.5 | BY20: 0.82 | BZ20: 0.65 | CA20: 5667 | CB20: 4469 | CC20: 4113 | CF20: 0 | CN20: 0 | FR20: 1485.7143 | FU20: 41.17 | FV20: 2140840 | FW20: 0 | FX20: 2140840 | FY20: 0 | FZ20: 0 | GA20: -2667816.3 | GB20: -156000 | GC20: 0 | GD20: -8563.36 | GE20: -6760 | GF20: -2839139.6 | GG20: -54.598839 | GH20: -698299.63 | GI20: -13.428839 | GK20: HBA II
B21: 16 | C21: 46204 | D21: EBP | E21: MV. VINCA | F21: MARUBENI-TOSOH (JFY2024) | G21: TOSOH #04 | H21: BoCT | J21: 46231.25 | K21: 46233.997 | L21: 46234.994 | N21: 1475.28 | S21: 23003.63 | AB21: 7502.24 | AH21: 7502.85 | AL21: 5116 | BJ21: 44600 | BL21: 46229 | BM21: 46238 | BO21: 0.28293386 | BQ21: Completed | BU21: 14.23 | BV21: 8.59 | BW21: 4.29 | BX21: 4.03 | BY21: 0.88 | BZ21: 0.83 | CA21: 6688 | CB21: 6276 | CC21: 5980 | CF21: 0.57 | CN21: -0.86797537 | FR21: 1862.2129 | FU21: 142.02 | FV21: 6334092 | FW21: 25422 | FX21: 6359514 | FY21: -38711.701 | FZ21: -68282.601 | GA21: -5238330.6 | GB21: -133800 | GC21: 0 | GD21: -25336.368 | GE21: -5798 | GF21: -5510259.3 | GG21: -123.54842 | GH21: 849254.69 | GI21: 19.041585 | GK21: HBA
B22: 17 | C22: 46204 | D22: EBP | E22: BG. PACIFIC 3019 | F22: BBS PLNBN (4600GAR/TS 1.5% max) Barge | G22: PLNBN BARGE JUL #01 | H22: BoCT | J22: 46208.653 | K22: 46212.374 | L22: 46212.512 | R22: 3752.62 | BI22: 3750 | BJ22: 7502.62 | BO22: 0.49982539 | BQ22: Completed | BU22: 33.13 | BV22: 13.69 | BW22: 5.82 | BX22: 4.51 | BY22: 1.22 | BZ22: 0.95 | CA22: 5709 | CB22: 4423 | CC22: 4066 | CF22: 0 | CN22: 0 | FR22: 2262.0965 | FU22: 41.17 | FV22: 308882.87 | FW22: 0 | FX22: 308882.87 | FY22: 0 | FZ22: 0 | GA22: -356326.69 | GB22: -22507.86 | GC22: 0 | GD22: -1235.5315 | GE22: -975.3406 | GF22: -381045.42 | GG22: -50.788314 | GH22: -72162.552 | GI22: -9.6183136 | GK22: HBA II
B23: 18 | C23: 46204 | D23: EBP | E23: BG. GURITA 3009 | F23: BBS PLNBN (4600GAR/TS 1.5% max) Barge | G23: PLNBN BARGE JUL #02 | H23: BoCT | J23: 46208.542 | K23: 46212.697 | L23: 46212.847 | R23: 3758.15 | BI23: 3751 | BJ23: 7509.15 | BO23: 0.49952391 | BQ23: Completed | BU23: 33.13 | BV23: 13.69 | BW23: 5.82 | BX23: 4.51 | BY23: 1.22 | BZ23: 0.95 | CA23: 5709 | CB23: 4423 | CC23: 4065 | CF23: 0 | CN23: 0 | FR23: 2076.2627 | FU23: 41.17 | FV23: 309151.71 | FW23: 0 | FX23: 309151.71 | FY23: 0 | FZ23: 0 | GA23: -356663.68 | GB23: -22527.45 | GC23: 0 | GD23: -1236.6068 | GE23: -976.1895 | GF23: -381403.92 | GG23: -50.79189 | GH23: -72252.216 | GI23: -9.6218901 | GK23: HBA II
B24: 19 | C24: 46204 | D24: EBP | E24: BG. PSB 3005 | F24: BBS PLNBN (4600GAR/TS 1.5% max) Barge | G24: PLNBN BARGE JUL #03 | H24: BoCT | J24: 46209.958 | K24: 46214.392 | L24: 46214.542 | R24: 3765.71 | BI24: 3752 | BJ24: 7517.71 | BO24: 0.49908815 | BQ24: Completed | BU24: 32.4 | BV24: 16.88 | BW24: 4.84 | BX24: 3.94 | BY24: 1.03 | BZ24: 0.84 | CA24: 5579 | CB24: 4537 | CC24: 4181 | CF24: 0 | CN24: 0 | FR24: 2097.9656 | FU24: 41.17 | FV24: 309504.12 | FW24: 0 | FX24: 309504.12 | FY24: 0 | FZ24: 0 | GA24: -357109.11 | GB24: -22553.13 | GC24: 0 | GD24: -1238.0165 | GE24: -977.3023 | GF24: -381877.56 | GG24: -50.79706 | GH24: -72373.442 | GI24: -9.6270596 | GK24: HBA II
B25: 20 | C25: 46204 | D25: EBP | E25: BG. BAIDURI 70273 | F25: BBS PLNBN (4600GAR/TS 1.5% max) Barge | G25: PLNBN BARGE JUL #04 | H25: BoCT | J25: 46209.271 | K25: 46214.706 | L25: 46214.84 | R25: 3759.78 | BI25: 3753 | BJ25: 7512.78 | BO25: 0.49954877 | BQ25: Completed | BU25: 31.73 | BV25: 15.53 | BW25: 5.73 | BX25: 4.63 | BY25: 1.24 | BZ25: 1 | CA25: 5523 | CB25: 4463 | CC25: 4111 | CF25: 0 | CN25: 0 | FR25: 2335.5793 | FU25: 41.17 | FV25: 309301.15 | FW25: 0 | FX25: 309301.15 | FY25: 0 | FZ25: 0 | GA25: -356833.87 | GB25: -22538.34 | GC25: 0 | GD25: -1237.2046 | GE25: -976.6614 | GF25: -381586.08 | GG25: -50.791595 | GH25: -72284.928 | GI25: -9.6215952 | GK25: HBA II
B26: 21 | C26: 46204 | D26: EBP | E26: BG. INTAN KELANA 19 | F26: BBS PLNBN (4600GAR/TS 1.5% max) Barge | G26: PLNBN BARGE JUL #05 | H26: BoCT | J26: 46213.354 | K26: 46218.324 | L26: 46218.5 | R26: 3776.68 | BI26: 3750 | BJ26: 7526.68 | BO26: 0.49822764 | BQ26: Completed | BU26: 32.5 | BV26: 17.07 | BW26: 5.68 | BX26: 4.63 | BY26: 1.14 | BZ26: 0.93 | CA26: 5510 | CB26: 4485 | CC26: 4130 | CF26: 0 | CN26: 0 | FR26: 1784.9834 | FU26: 41.17 | FV26: 309873.42 | FW26: 0 | FX26: 309873.42 | FY26: 0 | FZ26: 0 | GA26: -357612.05 | GB26: -22580.04 | GC26: 0 | GD26: -1239.4937 | GE26: -978.4684 | GF26: -382410.05 | GG26: -50.807268 | GH26: -72536.632 | GI26: -9.637268 | GK26: HBA II
B27: 22 | C27: 46204 | D27: EBP | E27: BG. ALARA 107 | F27: BBS PLNBN (4600GAR/TS 1.5% max) Barge | G27: PLNBN BARGE JUL #06 | H27: BoCT | J27: 46212 | K27: 46219.83 | L27: 46220.014 | R27: 3763.45 | BI27: 3750 | BJ27: 7513.45 | BO27: 0.49910494 | BQ27: Completed | BU27: 32.5 | BV27: 17.07 | BW27: 5.68 | BX27: 4.63 | BY27: 1.14 | BZ27: 0.93 | CA27: 5510 | CB27: 4485 | CC27: 4130 | CF27: 0 | CN27: 0 | FR27: 1701.1585 | FU27: 41.17 | FV27: 309328.74 | FW27: 0 | FX27: 309328.74 | FY27: 0 | FZ27: 0 | GA27: -356905.26 | GB27: -22540.35 | GC27: 0 | GD27: -1237.3149 | GE27: -976.7485 | GF27: -381659.67 | GG27: -50.79686 | GH27: -72330.935 | GI27: -9.6268604 | GK27: HBA II
B28: 23 | C28: 46204 | D28: EBP | E28: BG. SEGARA 81 | F28: BBS PLNBN (4600GAR/TS 1.5% max) Barge | G28: PLNBN BARGE JUL #07 | H28: BoCT | J28: 46216.163 | K28: 46221.396 | L28: 46221.528 | R28: 3761.64 | BI28: 3750 | BJ28: 7511.64 | BO28: 0.4992252 | BQ28: Completed | BU28: 33.07 | BV28: 13.6 | BW28: 5.45 | BX28: 4.22 | BY28: 1.19 | BZ28: 0.92 | CA28: 5749 | CB28: 4453 | CC28: 4096 | CF28: 0 | CN28: 0 | FR28: 2372.0968 | FU28: 41.17 | FV28: 309254.22 | FW28: 0 | FX28: 309254.22 | FY28: 0 | FZ28: 0 | GA28: -356808.56 | GB28: -22534.92 | GC28: 0 | GD28: -1237.0169 | GE28: -976.5132 | GF28: -381557.01 | GG28: -50.795434 | GH28: -72302.793 | GI28: -9.6254337 | GK28: HBA II
B29: 24 | C29: 46204 | D29: EBP | E29: BG. ASIA PERDANA 3005 | F29: BBS PLNBN (4600GAR/TS 1.5% max) Barge | G29: PLNBN BARGE JUL #08 | H29: BoCT | J29: 46217.375 | K29: 46221.72 | L29: 46221.872 | R29: 3761.9 | BI29: 3750 | BJ29: 7511.9 | BO29: 0.49920792 | BQ29: Completed | BU29: 33.07 | BV29: 13.6 | BW29: 5.45 | BX29: 4.22 | BY29: 1.19 | BZ29: 0.92 | CA29: 5749 | CB29: 4453 | CC29: 4096 | CF29: 0 | CN29: 0 | FR29: 2058.0548 | FU29: 41.17 | FV29: 309264.92 | FW29: 0 | FX29: 309264.92 | FY29: 0 | FZ29: 0 | GA29: -356822.45 | GB29: -22535.7 | GC29: 0 | GD29: -1237.0597 | GE29: -976.547 | GF29: -381571.76 | GG29: -50.795639 | GH29: -72306.835 | GI29: -9.6256387 | GK29: HBA II
B30: 25 | C30: 46204 | D30: EBP | E30: BG. PACIFIC 3036 | F30: BBS PLNBN (4600GAR/TS 1.5% max) Barge | G30: PLNBN BARGE JUL #10 | H30: BoCT | J30: 46222.535 | K30: 46223.463 | L30: 46223.598 | R30: 3753 | BI30: 3750 | BJ30: 7503 | BO30: 0.49980008 | BQ30: Completed | BU30: 33.42 | BV30: 13.76 | BW30: 5.3 | BX30: 4.09 | BY30: 1.22 | BZ30: 0.95 | CA30: 5730 | CB30: 4423 | CC30: 4065 | CF30: 0 | CN30: 0 | FR30: 2320.5155 | FU30: 41.17 | FV30: 308898.51 | FW30: 0 | FX30: 308898.51 | FY30: 0 | FZ30: 0 | GA30: -356346.99 | GB30: -22509 | GC30: 0 | GD30: -1235.594 | GE30: -975.39 | GF30: -381066.97 | GG30: -50.788614 | GH30: -72168.46 | GI30: -9.6186139 | GK30: HBA II
B31: 26 | C31: 46204 | D31: EBP | E31: BG. BENAMI XVI | F31: BBS PLNBN (4600GAR/TS 1.5% max) Barge | G31: PLNBN BARGE JUL #09 | H31: BoCT | J31: 46223.135 | K31: 46223.681 | L31: 46223.824 | R31: 3753 | BI31: 3750 | BJ31: 7503 | BO31: 0.49980008 | BQ31: Completed | BU31: 33.42 | BV31: 13.76 | BW31: 5.3 | BX31: 4.09 | BY31: 1.22 | BZ31: 0.95 | CA31: 5730 | CB31: 4423 | CC31: 4065 | CF31: 0 | CN31: 0 | FR31: 2185.3398 | FU31: 41.17 | FV31: 308898.51 | FW31: 0 | FX31: 308898.51 | FY31: 0 | FZ31: 0 | GA31: -356346.99 | GB31: -22509 | GC31: 0 | GD31: -1235.594 | GE31: -975.39 | GF31: -381066.97 | GG31: -50.788614 | GH31: -72168.46 | GI31: -9.6186139 | GK31: HBA II
B32: 27 | C32: 46204 | D32: EBP | E32: MV. ASTER OCEAN | F32: ZHEJIANG (5500NAR/TS 1.5%max) | G32: ZHEJIANG 5500NAR #2/5 | H32: Muara Berau | J32: 46198.675 | K32: 46202.698 | L32: 46205.342 | R32: 7611.72 | T32: 7351.75 | U32: 36157.85 | V32: 7504.62 | W32: 7633.18 | AW32: 4708.88 | BJ32: 70968 | BL32: 46198 | BM32: 46207 | BO32: 0.066352159 | BQ32: Completed | BS32: RockTree Zeus | BU32: 18.031996 | BV32: 10.332374 | BW32: 5.2418784 | BX32: 4.7917663 | BY32: 0.97964792 | BZ32: 0.89552705 | CA32: 6427.6633 | CB32: 5875.7297 | CC32: 5567.6202 | CF32: 0.87 | CN32: -0.47260634 | FR32: 1118.487 | FU32: 103.93 | FV32: 7375704.2 | FW32: 61742.16 | FX32: 7437446.4 | FY32: -33539.927 | FZ32: 0 | GA32: -7549835.9 | GB32: -220785.29 | GC32: 0 | GD32: -29502.817 | GE32: -9225.84 | GF32: -7842889.8 | GG32: -110.51304 | GH32: -405443.35 | GI32: -5.7130446 | GK32: HBA I
B33: 28 | C33: 46204 | D33: EBP | E33: MV. IRIS WAVE | F33: EPDC (1.2%) | G33: EPDC #2/6 | H33: Muara Berau | J33: 46200.814 | K33: 46203.59 | L33: 46205.5 | S33: 18742.04 | T33: 12494.69 | AB33: 14946.62 | AH33: 15013.65 | AJ33: 7503 | BJ33: 68700 | BL33: 46194 | BM33: 46203 | BO33: 0.32775328 | BQ33: Completed | BS33: PNTS WHS Iskandar_O | BU33: 15.628188 | BV33: 8.9140353 | BW33: 3.9710382 | BX33: 3.678324 | BY33: 1.1461257 | BZ33: 1.0616422 | CA33: 6658.5525 | CB33: 6167.7355 | CC33: 5867.4841 | CF33: 4.53 | CN33: -0.21367448 | FR33: 1498.9091 | FU33: 129.96 | FV33: 8928252 | FW33: 311211 | FX33: 9239463 | FY33: -14679.437 | FZ33: -113215.39 | GA33: -7942706.7 | GB33: -252816 | GC33: 0 | GD33: -35713.008 | GE33: -8931 | GF33: -8368061.6 | GG33: -121.80585 | GH33: 871401.44 | GI33: 12.684155 | GK33: HBA
B34: 29 | C34: 46204 | D34: EBP | E34: MV. SILVERGATE | F34: MARUBENI (KOBE) DUMMY | G34: KOBE #02 | H34: Muara Berau | J34: 46202.833 | K34: 46203.781 | L34: 46205.417 | S34: 27495.64 | U34: 14901.22 | AC34: 7502.36 | AH34: 7500.78 | BJ34: 57400 | BL34: 46196 | BM34: 46205 | BO34: 0.26137875 | BQ34: Completed | BS34: RockTree Apollo | BU34: 14.286211 | BV34: 8.2198298 | BW34: 4.1377977 | BX34: 3.8643022 | BY34: 0.71734737 | BZ34: 0.66993296 | CA34: 6698.0675 | CB34: 6255.3462 | CC34: 5959.4816 | CF34: 1.72 | CN34: 0.04759661 | FR34: 1462.4204 | FU34: 130.94 | FV34: 7515956 | FW34: 98728 | FX34: 7614684 | FY34: 2732.0454 | FZ34: -80301.905 | GA34: -6787145.3 | GB34: -178574.51 | GC34: 0 | GD34: -30063.824 | GE34: -7462 | GF34: -7080815.5 | GG34: -123.35916 | GH34: 533868.49 | GI34: 9.3008448 | GK34: HBA
B35: 30 | C35: 46204 | D35: EBP | E35: MV. LUMOSO KARUNIA IX | F35: FREEPORT | G35: FREEPORT #1/4 | H35: Muara Berau | J35: 46200.229 | K35: 46206.698 | L35: 46209.646 | Q35: 5002.3 | R35: 2501.65 | S35: 10337.85 | U35: 7461.04 | AB35: 15289.99 | AH35: 15007.17 | BJ35: 55600 | BL35: 46205 | BM35: 46214 | BO35: 0.26991313 | BQ35: Completed | BS35: RockTree Apollo | BU35: 15.334982 | BV35: 9.0913199 | BW35: 4.2905701 | BX35: 3.9958912 | BY35: 0.99972996 | BZ35: 0.93106792 | CA35: 6623.8184 | CB35: 6168.8906 | CC35: 5869.5977 | CF35: 4.06 | CN35: -0.42567668 | FR35: 785.86572 | FU35: 136.97 | FV35: 7615532 | FW35: 225736 | FX35: 7841268 | FY35: -23667.624 | FZ35: -82035.786 | GA35: -6402190.8 | GB35: -172974.61 | GC35: 0 | GD35: -30462.128 | GE35: -7228 | GF35: -6718559 | GG35: -120.83739 | GH35: 1122709 | GI35: 20.192608 | GK35: HBA
B36: 31 | C36: 46204 | D36: EBP | E36: MV. BOGA INDAH | F36: MARUBENI (TOKUYAMA-TCM) | G36: TOKUYAMA #06 | H36: Muara Berau | J36: 46207.375 | K36: 46208.8 | L36: 46212.465 | T36: 13607.88 | U36: 7528.06 | AB36: 22679.06 | AF36: 7500 | BJ36: 51315 | BL36: 46207 | BM36: 46216 | BO36: 0.14615609 | BQ36: Completed | BS36: RockTree Apollo | BU36: 14.528463 | BV36: 7.5479635 | BW36: 3.7564615 | BX36: 3.4728336 | BY36: 1.3238974 | BZ36: 1.2239378 | CA36: 6821.7477 | CB36: 6306.6784 | CC36: 6010.0219 | CF36: 2.23 | CN36: -0.85416782 | FR36: 583.34596 | FU36: 143.77 | FV36: 7377557.6 | FW36: 114432.45 | FX36: 7491990 | FY36: -43831.621 | FZ36: -29923.589 | GA36: -5980730.4 | GB36: -159643.74 | GC36: 0 | GD36: -29510.23 | GE36: -6670.95 | GF36: -6250310.5 | GG36: -121.8028 | GH36: 1241679.5 | GI36: 24.197204 | GK36: HBA
B37: 32 | C37: 46204 | D37: EBP | E37: MV. BOGA INDAH | F37: MARUBENI (TOKUYAMA-TCM) - MCV | G37: TOKUYAMA #06 (MCV) | H37: Muara Berau | J37: 46207.375 | K37: 46210.792 | L37: 46211.771 | Q37: 4505.42 | R37: 3000.95 | V37: 253.29 | W37: 14055.34 | BJ37: 21815 | BL37: 46207 | BM37: 46216 | BO37: 0 | BQ37: Completed | BS37: RockTree Apollo | BU37: 18.33197 | BV37: 11.519207 | BW37: 4.6998668 | BX37: 4.3379908 | BY37: 0.82106471 | BZ37: 0.75784512 | CA37: 6271.2337 | CB37: 5788.367 | CC37: 5479.277 | CF37: 1.9 | CN37: -3.1083875 | FR37: 928.29787 | FU37: 116.93 | FV37: 2550828 | FW37: 41448.5 | FX37: 2592276.5 | FY37: -67809.472 | FZ37: 0 | GA37: -2373602.1 | GB37: -67867.646 | GC37: 0 | GD37: -10203.312 | GE37: -2835.95 | GF37: -2522318.5 | GG37: -115.62313 | GH37: 69957.932 | GI37: 3.2068729 | GK37: HBA I
B38: 33 | C38: 46204 | D38: EBP | E38: MV. NEW HARMONY 8 | F38: SHENHUA (5200NAR/TS max 1.0%) | G38: SHENHUA 5200NAR #2/4 | H38: Muara Berau | J38: 46208.75 | K38: 46209.517 | L38: 46211.66 | R38: 7508.39 | U38: 32290.53 | W38: 24579.05 | Y38: 7501.03 | AV38: 5121 | BJ38: 77000 | BL38: 46200 | BM38: 46209 | BO38: 0.066506494 | BQ38: Completed | BS38: PNTS WHS Iskandar_O | BU38: 21.000106 | BV38: 12.111607 | BW38: 5.120237 | BX38: 4.6024073 | BY38: 0.51910516 | BZ38: 0.46660602 | CA38: 6187.8022 | CB38: 5562.0055 | CC38: 5244.1934 | CF38: 3.16 | CN38: 0.13202561 | FR38: 1497.5689 | FU38: 100.2 | FV38: 7715400 | FW38: 243320 | FX38: 7958720 | FY38: 10165.972 | FZ38: 0 | GA38: -7815344.4 | GB38: -283360 | GC38: 0 | GD38: -30861.6 | GE38: -10010 | GF38: -8129410 | GG38: -105.57675 | GH38: -170690.05 | GI38: -2.2167539 | GK38: HBA I
B39: 34 | C39: 46204 | D39: EBP | E39: MV. AGP KARTINI III | F39: BBS PLNBN (4600GAR/TS 1.5% max) DUMMY | G39: PLNBN AUG #04 | H39: Muara Berau | J39: 46212.542 | K39: 46213.896 | L39: 46220.5 | U39: 22494.86 | Y39: 22505.14 | BI39: 7500 | BJ39: 52500 | BL39: 46199 | BM39: 46208 | BO39: 0.14285714 | BQ39: Completed | BS39: Stevedore | BU39: 30.720602 | BV39: 16.580388 | BW39: 5.5009146 | BX39: 4.5684707 | BY39: 0.27904586 | BZ39: 0.23174562 | CA39: 5648.116 | CB39: 4690.7204 | CC39: 4341.1322 | CF39: 0 | CN39: 0 | FR39: 331.23028 | FU39: 41.17 | FV39: 2161425 | FW39: 0 | FX39: 2161425 | FY39: 0 | FZ39: 0 | GA39: -2906553.7 | GB39: -64050 | GC39: 0 | GD39: -8645.7 | GE39: -6825 | GF39: -2986074.4 | GG39: -56.877608 | GH39: -824649.42 | GI39: -15.707608 | GK39: HBA II
B40: 35 | C40: 46204 | D40: EBP | E40: MV. ORIENTAL PROMOTION | F40: ZHEJIANG (5200NAR/TS 1.0%max) | G40: ZHEJIANG 5200NAR TS 1% max #6/11 | H40: Muara Berau | J40: 46212.653 | K40: 46214.038 | L40: 46216.671 | R40: 7508.17 | U40: 27270.555 | V40: 19614.675 | Y40: 7501.6 | AQ40: 7509 | BJ40: 69404 | BL40: 46212 | BM40: 46221 | BO40: 0.10819261 | BQ40: Completed | BS40: RockTree Zeus | BU40: 20.31582 | BV40: 11.549476 | BW40: 5.3322511 | BX40: 4.803771 | BY40: 0.91482247 | BZ40: 0.82415428 | CA40: 6248.7056 | CB40: 5629.3955 | CC40: 5313.8203 | CF40: 2.48 | CN40: 0.044532216 | FR40: 1098.4542 | FU40: 97.05 | FV40: 6735658.2 | FW40: 172121.92 | FX40: 6907780.1 | FY40: 3090.7139 | FZ40: -31859.719 | GA40: -6714440.5 | GB40: -215919.6 | GC40: 0 | GD40: -26942.633 | GE40: -9022.52 | GF40: -6995094.3 | GG40: -100.78806 | GH40: -87314.159 | GI40: -1.2580566 | GK40: HBA I
B41: 36 | C41: 46204 | D41: EBP | E41: MV. ALPHA PROGRESS | F41: HO PING POWER 5900 GAR (TS(max) 0.95%) | G41: HO PING POWER #3/4 | H41: Muara Berau | J41: 46215.162 | K41: 46215.677 | L41: 46217.778 | S41: 11572.815 | T41: 3857.605 | U41: 42757.17 | AH41: 15002.41 | BJ41: 73190 | BL41: 46206 | BM41: 46215 | BO41: 0.20497896 | BQ41: Completed | BS41: RockTree Apollo | BU41: 15.210226 | BV41: 9.6230356 | BW41: 4.4457033 | BX41: 4.1708657 | BY41: 0.76453087 | BZ41: 0.71726684 | CA41: 6551.287 | CB41: 6146.2802 | CC41: 5847.3951 | CF41: 5.65 | CN41: -0.042511163 | FR41: 1451.7025 | FU41: 107.51 | FV41: 7868656.9 | FW41: 413523.5 | FX41: 8282180.4 | FY41: -3111.392 | FZ41: -82009.765 | GA41: -8201377.3 | GB41: -227698.05 | GC41: 0 | GD41: -31474.628 | GE41: -9514.7 | GF41: -8555185.9 | GG41: -116.89009 | GH41: -273005.47 | GI41: -3.7300925 | GK41: HBA
B42: 37 | C42: 46204 | D42: EBP | E42: MV. TOHOKU MARU | F42: TOHOKU | G42: TOHOKU #3/4 | H42: Muara Berau | J42: 46216.5 | K42: 46216.901 | L42: 46219.341 | N42: 7624.62 | S42: 38313.06 | T42: 12059.81 | W42: 22570.92 | AH42: 7501.59 | BJ42: 88070 | BL42: 46208 | BM42: 46217 | BO42: 0.085177586 | BQ42: Completed | BS42: RockTree Zeus | BU42: 14.611521 | BV42: 7.8164939 | BW42: 4.3817176 | BX42: 4.0587326 | BY42: 0.826833 | BZ42: 0.76588552 | CA42: 6735.9979 | CB42: 6239.4743 | CC42: 5942.5463 | CF42: 2.69 | CN42: -0.01871939 | FR42: 1504.1845 | FU42: 136.96 | FV42: 12062067 | FW42: 236908.3 | FX42: 12298976 | FY42: -1648.6167 | FZ42: -41006.987 | GA42: -10434861 | GB42: -273990.54 | GC42: 0 | GD42: -48248.269 | GE42: -11449.1 | GF42: -10811204 | GG42: -122.75695 | GH42: 1487771.1 | GI42: 16.893052 | GK42: HBA
B43: 38 | C43: 46204 | D43: EBP | E43: MV. SEACON NOLA | F43: JERA TRADING INC (1.3%) | G43: JERA #3/6 (TS rej 1.3%) | H43: Muara Berau | J43: 46219.083 | K43: 46219.639 | L43: 46221.403 | S43: 24169.28 | T43: 10938.03 | AB43: 15090.78 | AH43: 7501.91 | AJ43: 7500 | BJ43: 65200 | BL43: 46217 | BM43: 46226 | BO43: 0.23009064 | BQ43: Completed | BS43: RockTree Apollo | BU43: 13.800914 | BV43: 6.9548497 | BW43: 4.5109424 | BX43: 4.1790368 | BY43: 1.0256837 | BZ43: 0.95021603 | CA43: 6894.8666 | CB43: 6387.557 | CC43: 6093.2789 | CF43: 0.83 | CN43: 0.082775051 | FR43: 1540.1575 | FU43: 134.27 | FV43: 8754404 | FW43: 54116 | FX43: 8808520 | FY43: 5396.9333 | FZ43: -72140.47 | GA43: -7676792 | GB43: -202840.73 | GC43: 0 | GD43: -35017.616 | GE43: -8476 | GF43: -7989869.9 | GG43: -122.54402 | GH43: 818650.1 | GI43: 12.555983 | GK43: HBA
B44: 39 | C44: 46204 | D44: EBP | E44: MV. CHANG SHENG HAI | F44: ZHEJIANG (5500NAR/TS 1.5%max) | G44: ZHEJIANG 5500NAR #3/5 | H44: Muara Berau | J44: 46220.792 | K44: 46221.012 | L44: 46223.007 | R44: 15016.45 | U44: 17273.508 | V44: 32079.372 | AT44: 7580.67 | BJ44: 71950 | BL44: 46219 | BM44: 46228 | BO44: 0.10536025 | BQ44: Completed | BS44: RockTree Zeus | BU44: 17.667823 | BV44: 9.9386215 | BW44: 5.7688081 | BX44: 5.2737204 | BY44: 1.2669353 | BZ44: 1.158205 | CA44: 6371.2979 | CB44: 5824.5036 | CC44: 5517.5847 | CF44: 1.85 | CN44: 0.23169926 | FR44: 1503.1337 | FU44: 100.66 | FV44: 7242487 | FW44: 133107.5 | FX44: 7375594.5 | FY44: 16670.761 | FZ44: 0 | GA44: -7301499.6 | GB44: -223840.35 | GC44: 0 | GD44: -28969.948 | GE44: -9353.5 | GF44: -7546992.6 | GG44: -104.89218 | GH44: -171398.14 | GI44: -2.382184 | GK44: HBA I
B45: 40 | C45: 46204 | D45: BEK | E45: MV. STRATEGIC HARMONY | F45: TENAGA NATIONAL BERHAD (6150 GAR) | G45: TNB JANAMANJUNG #BO | H45: Muara Berau | J45: 46222.802 | K45: 46224.667 | L45: 46226.438 | U45: 33000 | BJ45: 33000 | BL45: 46223 | BM45: 46232 | BO45: 1 | BQ45: Completed | BS45: Stevedore | BU45: 14.027638 | BV45: 9.0755777 | BW45: 4.9051645 | BX45: 4.6380122 | BY45: 0.64245101 | BZ45: 0.60746089 | CA45: 6702.3347 | CB45: 6337.3023 | CC45: 6042.283 | CF45: 2.98 | CN45: -0.65246212 | FR45: 776.47059 | FU45: 122.97 | FV45: 4058010 | FW45: 98340 | FX45: 4156350 | FY45: -21531.25 | FZ45: -177031.87 | GA45: -1850046.3 | GB45: -40260 | GC45: -547831.35 | GD45: 0 | GE45: 0 | GF45: -2636700.8 | GG45: -79.900023 | GH45: 1519649.2 | GI45: 46.049977 | GK45: HBA
B46: 41 | C46: 46204 | D46: EBP | E46: MV. ASL MERCURY | F46: MARUBENI (KOBE) DUMMY | G46: KOBE #03 | H46: Muara Berau | J46: 46221.604 | K46: 46224.91 | L46: 46226.896 | S46: 30017.22 | U46: 14734.72 | AC46: 7645.83 | AH46: 7502.23 | BJ46: 59900 | BL46: 46217 | BM46: 46226 | BO46: 0.25288915 | BQ46: Completed | BS46: PNTS WHS Iskandar_O | BU46: 12.890702 | BV46: 7.6506396 | BW46: 4.7784074 | BX46: 4.5072723 | BY46: 0.73481286 | BZ46: 0.69311831 | CA46: 6806.2003 | CB46: 6420.0047 | CC46: 6128.7021 | CF46: 4.9 | CN46: -0.29193911 | FR46: 1256.6434 | FU46: 142.02 | FV46: 8506998 | FW46: 293510 | FX46: 8800508 | FY46: -17487.153 | FZ46: -81061.365 | GA46: -7102816.4 | GB46: -220432 | GC46: 0 | GD46: -34027.992 | GE46: -7787 | GF46: -7463611.9 | GG46: -124.6012 | GH46: 1336896.1 | GI46: 22.3188 | GK46: HBA
B47: 42 | C47: 46204 | D47: BEK | E47: MV. HL LEADER | F47: KOWEPO (CV 5850NAR) | G47: KOWEPO JUN #SPOT | H47: Muara Berau | J47: 46223.431 | K47: 46223.66 | L47: 46228.833 | U47: 54112.579 | V47: 25812.421 | BJ47: 79925 | BL47: 46217 | BM47: 46226 | BO47: 1 | BQ47: Completed | BS47: FC Pioneer Satu | BU47: 14.592212 | BV47: 8.6491272 | BW47: 5.3831197 | BX47: 5.0329059 | BY47: 0.86078437 | BZ47: 0.80478365 | CA47: 6708.6146 | CB47: 6272.167 | CC47: 5975.3022 | CF47: 0 | CN47: -0.24061645 | FR47: 643.69128 | FU47: 123.03 | FV47: 9833172.8 | FW47: 0 | FX47: 9833172.8 | FY47: -19231.27 | FZ47: -428765.83 | GA47: -4200861.1 | GB47: -157452.25 | GC47: -1327478.3 | GD47: 0 | GE47: 0 | GF47: -6133788.7 | GG47: -76.744307 | GH47: 3699384 | GI47: 46.285693 | GK47: HBA
B48: 43 | C48: 46204 | D48: EBP | E48: MV. YM IMPRESSION | F48: JERA TRADING INC (1.3%) | G48: JERA #SPOT (TS rej 1.3%) | H48: Muara Berau | J48: 46224.667 | K48: 46224.925 | L48: 46228.927 | N48: 7788.32 | S48: 12736.669 | T48: 10420.911 | AB48: 15090.83 | AC48: 7643.27 | AF48: 7500 | BJ48: 61180 | BL48: 46210 | BM48: 46231 | BO48: 0.24751994 | BQ48: Completed | BS48: RockTree Zeus | BU48: 12.80022 | BV48: 6.6446787 | BW48: 4.5917239 | BX48: 4.2889608 | BY48: 1.0506995 | BZ48: 0.98141986 | CA48: 6898.6245 | CB48: 6443.752 | CC48: 6152.7451 | CF48: 3.2 | CN48: -0.61062719 | FR48: 636.95992 | FU48: 125.54 | FV48: 7680537.2 | FW48: 195776 | FX48: 7876313.2 | FY48: -37358.172 | FZ48: -69961.058 | GA48: -7275172.1 | GB48: -190334.29 | GC48: 0 | GD48: -30722.149 | GE48: -7953.4 | GF48: -7611501.2 | GG48: -124.41159 | GH48: 264812.01 | GI48: 4.3284082 | GK48: HBA
B49: 44 | C49: 46204 | D49: EBP | E49: MV. KELLY | F49: THERMA LUZON (5700GAR/TS 0.85% max) | G49: THERMA LUZON 5700GAR TS 0.85% max #1/2 | H49: Muara Berau | J49: 46220.604 | K49: 46226.375 | L49: 46230.045 | S49: 5487.9 | T49: 1829.3 | U49: 37969.065 | V49: 10908.735 | AF49: 15000 | AQ49: 7505 | BJ49: 78700 | BL49: 46222 | BM49: 46231 | BO49: 0.28595934 | BQ49: Completed | BS49: RockTree Apollo | BU49: 17.746487 | BV49: 10.270662 | BW49: 5.0353181 | BX49: 4.6157992 | BY49: 0.79121424 | BZ49: 0.72529401 | CA49: 6396.4249 | CB49: 5863.505 | CC49: 5556.3289 | CF49: 2.8 | CN49: -0.98409511 | FR49: 893.47209 | FU49: 120.02 | FV49: 9445574 | FW49: 220360 | FX49: 9665934 | FY49: -77448.285 | FZ49: -91689.925 | GA49: -8078347.6 | GB49: -244839.96 | GC49: 0 | GD49: -37782.296 | GE49: -10231 | GF49: -8540339 | GG49: -108.51765 | GH49: 1125595 | GI49: 14.30235 | GK49: HBA I
B50: 45 | C50: 46204 | D50: EBP | E50: MV. TAIRYU | F50: EPDC (1.2%) | G50: EPDC #3/6 | H50: Muara Berau | J50: 46225.925 | K50: 46228.431 | L50: 46231.208 | S50: 13595.705 | T50: 13595.705 | W50: 7591.45 | AB50: 15009.83 | AF50: 7500 | AH50: 7501.31 | AL50: 5119 | BJ50: 69913 | BL50: 46223 | BM50: 46232 | BO50: 0.28779068 | BQ50: Completed | BS50: PNTS WHS Iskandar_O | BU50: 15.211606 | BV50: 9.0017333 | BW50: 4.843476 | BX50: 4.5129491 | BY50: 0.99186674 | BZ50: 0.9241801 | CA50: 6587.1068 | CB50: 6137.5917 | CC50: 5838.7021 | CF50: 1.4 | CN50: -0.16390951 | FR50: 1048.695 | FU50: 129.96 | FV50: 9085893.5 | FW50: 97878.2 | FX50: 9183771.7 | FY50: -11459.406 | FZ50: -98213.762 | GA50: -7955292.8 | GB50: -257279.84 | GC50: 0 | GD50: -36343.574 | GE50: -9088.69 | GF50: -8367678.1 | GG50: -119.68701 | GH50: 816093.6 | GI50: 11.672988 | GK50: HBA
B51: 46 | C51: 46204 | D51: EBP | E51: MV. SUNSHINE PRIDE | F51: JOBAN JOINT POWER (BEK) TS max 0.75% | G51: JOBAN #2/3 | H51: Muara Berau | J51: 46229.024 | K51: 46230.292 | L51: 46231.965 | S51: 14073.973 | T51: 1125.477 | U51: 42538.53 | AH51: 7502.02 | BJ51: 65240 | BL51: 46224 | BM51: 46233 | BO51: 0.11499111 | BQ51: Completed | BS51: RockTree Zeus | BU51: 15.072429 | BV51: 9.1522331 | BW51: 5.1151111 | BX51: 4.7817791 | BY51: 0.69903656 | BZ51: 0.65348306 | CA51: 6626.5483 | CB51: 6194.7219 | CC51: 5896.2872 | CF51: -1.92 | CN51: -0.061579041 | FR51: 1624.2324 | FU51: 141.4 | FV51: 9224936 | FW51: -125260.8 | FX51: 9099675.2 | FY51: -4017.4167 | FZ51: -41009.338 | GA51: -7387988.2 | GB51: -202965.17 | GC51: 0 | GD51: -36899.744 | GE51: -8481.2 | GF51: -7681361.1 | GG51: -117.74005 | GH51: 1418314.1 | GI51: 21.739947 | GK51: HBA
B52: 47 | C52: 46204 | D52: EBP | E52: MV. GOUVERNEUR | F52: ZHEJIANG (5500NAR/TS 1.5%max) | G52: ZHEJIANG 5500NAR #4/5 | H52: Muara Berau | J52: 46230.729 | K52: 46232.417 | L52: 46234.858 | R52: 15036.13 | V52: 14335.36 | W52: 39077.51 | AV52: 5001 | BJ52: 73450 | BL52: 46225 | BM52: 46234 | BO52: 0.068087134 | BQ52: Completed | BS52: PNTS WHS Iskandar_O | BU52: 18.169105 | BV52: 11.297674 | BW52: 5.3993254 | BX52: 4.9810603 | BY52: 0.96153372 | BZ52: 0.88704737 | CA52: 6197.6983 | CB52: 5717.5863 | CC52: 5409.0286 | CF52: -0.75 | CN52: 0.031015052 | FR52: 1253.7696 | FU52: 100.59 | FV52: 7388335.5 | FW52: -55087.5 | FX52: 7333248 | FY52: 2278.0556 | FZ52: 0 | GA52: -7711457.4 | GB52: -270296 | GC52: 0 | GD52: -29553.342 | GE52: -9548.5 | GF52: -8018577.2 | GG52: -109.17055 | GH52: -685329.2 | GI52: -9.3305541 | GK52: HBA I
B53: 48 | C53: 46204 | D53: TCM | E53: BG. MJL 308 | F53: INDOCEMENT (2024) | G53: INDOCEMENT TCM #04 | H53: Bunyut | J53: 46214.938 | K53: 46215.668 | L53: 46215.767 | S53: 4564.878 | T53: 3043.252 | BJ53: 7608.13 | BO53: 1 | BQ53: Completed | BU53: 10.99177 | BV53: 6.1454857 | BW53: 4.5294566 | BX53: 4.2978844 | BY53: 1.2300206 | BZ53: 1.1682601 | CA53: 7031.4823 | CB53: 6668.1203 | CC53: 6369.9147 | CF53: 0 | CN53: 0 | FR53: 3192.2224 | FU53: 94.23 | FV53: 716914.09 | FW53: 0 | FX53: 716914.09 | FY53: 0 | FZ53: -40340.196 | GA53: -521378.28 | GB53: 0 | GC53: -126199.48 | GD53: 0 | GE53: 0 | GF53: -687917.95 | GG53: -90.418795 | GH53: 28996.141 | GI53: 3.8112047 | GK53: HBA
GH54: 10680360
L58: Total Coal Loading of BoCT | N58: 18941.31 | O58: 0 | P58: 0 | Q58: 30915.18 | R58: 633510.06 | S58: 27521.02 | T58: 3011.6 | U58: 38243.46 | V58: 14940.54 | W58: 0 | X58: 0 | Y58: 127523.76 | Z58: 0 | AA58: 0 | AB58: 14968.38 | AC58: 0 | AD58: 0 | AE58: 0 | AF58: 0 | AG58: 0 | AH58: 15011.38 | AI58: 0 | AJ58: 0 | AK58: 0 | AL58: 5116 | AM58: 0 | AN58: 0 | AO58: 0 | AP58: 0 | AQ58: 15022 | AR58: 0 | AS58: 0 | AT58: 15168.34 | AU58: 0 | AV58: 10240 | AW58: 0 | AX58: 20324.9 | AY58: 0 | AZ58: 0 | BA58: 0 | BB58: 0 | BC58: 0 | BD58: 0 | BE58: 0 | BF58: 0 | BG58: 0 | BH58: 0 | BI58: 89875 | BJ58: 1080332.9 | CF58: -0.0087033991 | CN58: -0.30576386 | FR58: 2043.4548
L59: Total Coal Loading of Mahakam | N59: 15412.94 | O59: 0 | P59: 0 | Q59: 9507.72 | R59: 58183.46 | S59: 211107.03 | T59: 90324.41 | U59: 390489.69 | V59: 110508.47 | W59: 115507.45 | X59: 0 | Y59: 37507.77 | Z59: 0 | AA59: 0 | AB59: 98107.11 | AC59: 22791.46 | AD59: 0 | AE59: 0 | AF59: 37500 | AG59: 0 | AH59: 90033.07 | AI59: 0 | AJ59: 15003 | AK59: 0 | AL59: 5119 | AM59: 0 | AN59: 0 | AO59: 0 | AP59: 0 | AQ59: 15014 | AR59: 0 | AS59: 0 | AT59: 7580.67 | AU59: 0 | AV59: 10122 | AW59: 4708.88 | AX59: 0 | AY59: 0 | AZ59: 0 | BA59: 0 | BB59: 0 | BC59: 0 | BD59: 0 | BE59: 0 | BF59: 0 | BG59: 0 | BH59: 0 | BI59: 7500 | BJ59: 1352028.1 | CF59: 0.76995439 | CN59: -0.28852334 | FR59: 1210.4506
J60: Total Coal Loading of ITM (Coal Demand) | N60: 34354.25 | O60: 0 | P60: 0 | Q60: 40422.9 | R60: 691693.52 | S60: 238628.05 | T60: 93336.01 | U60: 428733.15 | V60: 125449.01 | W60: 115507.45 | X60: 0 | Y60: 165031.53 | Z60: 0 | AA60: 0 | AB60: 113075.49 | AC60: 22791.46 | AD60: 0 | AE60: 0 | AF60: 37500 | AG60: 0 | AH60: 105044.45 | AI60: 0 | AJ60: 15003 | AK60: 0 | AL60: 10235 | AM60: 0 | AN60: 0 | AO60: 0 | AP60: 0 | AQ60: 30036 | AR60: 0 | AS60: 0 | AT60: 22749.01 | AU60: 0 | AV60: 20362 | AW60: 4708.88 | AX60: 20324.9 | AY60: 0 | AZ60: 0 | BA60: 0 | BB60: 0 | BC60: 0 | BD60: 0 | BE60: 0 | BF60: 0 | BG60: 0 | BH60: 0 | BI60: 97375 | BJ60: 2432361.1 | BK60: 0 | CF60: 0.42411361 | CN60: -0.29618072
L62: Inventory | CF62: 0.76079081
L63: Total BOP (Beginning of Period) | N63: 32041.29 | O63: 0 | P63: 0 | Q63: 38073.69 | R63: 249358.13 | S63: 165544.56 | T63: 131618.94 | U63: 139770.27 | V63: 29457.648 | W63: 59927.443 | X63: 1370.339 | Y63: 89226.137 | Z63: 0 | AA63: 0 | AB63: 84748.566 | AC63: 7502.36 | AD63: 0 | AE63: 0 | AF63: 0 | AG63: 0 | AH63: 37525.47 | AI63: 0 | AJ63: 7503 | AK63: 0 | AL63: 0 | AM63: 0 | AN63: 0 | AO63: 0 | AP63: 0 | AQ63: 0 | AR63: 0 | AS63: 0 | AT63: 15168.34 | AU63: 0 | AV63: 0 | AW63: 4708.88 | AX63: 15224.91 | AY63: 0 | AZ63: 0 | BA63: 0 | BB63: 0 | BC63: 0 | BD63: 0 | BE63: 0 | BF63: 0 | BG63: 0 | BH63: 0 | BI63: 44868 | BJ63: 1153638 | CF63: 2.389235
L64: PSY at Barge Port (Bunyut and JBG) | S64: 102735.03 | T64: 100693.56 | U64: 16887.329 | V64: 21953.028 | W64: 27373.023 | X64: 1370.339 | Y64: 21712.377 | AB64: 47045.816 | BJ64: 339770.51
L65: PSY at Vessel Port (BoCT) | N65: 32041.29 | O65: 0 | P65: 0 | Q65: 38073.69 | R65: 241746.41 | S65: 4517.39 | T65: 3011.6 | AB65: 7466.14 | AH65: 7508.53 | AT65: 7553.14 | AX65: 5204.95 | BI65: 15004 | BJ65: 362127.14
L66: Coal on Water/Intransit (Barge,Vessel, Storage) | R66: 7611.72 | S66: 58292.14 | T66: 27913.78 | U66: 122882.94 | V66: 7504.62 | W66: 32554.42 | Y66: 67513.76 | AB66: 30236.61 | AC66: 7502.36 | AH66: 30016.94 | AJ66: 7503 | AT66: 7615.2 | AW66: 4708.88 | AX66: 10019.96 | BI66: 29864 | BJ66: 451740.33
L67: Monthly FC Production Plan | N67: 31631.429 | O67: 0 | P67: 0 | Q67: 37816.199 | R67: 571737.37 | S67: 205688 | T67: 100019 | U67: 443660 | V67: 184064.5 | W67: 164945 | X67: 0 | Y67: 192463 | Z67: 0 | AA67: 0 | AB67: 76294.66 | AC67: 15289.1 | AD67: 0 | AE67: 0 | AF67: 37500 | AG67: 0 | AH67: 67518.98 | AI67: 0 | AJ67: 15047 | AK67: 0 | AL67: 10235 | AM67: 0 | AN67: 0 | AO67: 0 | AP67: 0 | AQ67: 30036 | AR67: 0 | AS67: 0 | AT67: 22645.04 | AU67: 0 | AV67: 20362 | AW67: 0 | AX67: 10199.92 | AY67: 0 | AZ67: 0 | BA67: 0 | BB67: 65078 | BC67: 0 | BD67: 0 | BE67: 0 | BF67: 0 | BG67: 0 | BH67: 0 | BI67: 97520 | BJ67: 2399750.2
L68: Update Coal Flow as 31 July (Based on Report 1 Aug)
L69: PSY at Barge Port (Bunyut and JBG) | S69: 80904.649 | T69: 98139.307 | U69: 99914.85 | V69: 43681.79 | W69: 71947.57 | X69: 1370.339 | Y69: 56646 | AB69: 10419.496 | BJ69: 463024
L70: PSY at Vessel Port (BoCT) | N70: 27281.96 | O70: 0 | P70: 0 | Q70: 33304.36 | R70: 132792.5 | V70: 29813.7 | Y70: 22503.9 | AB70: 7540.53 | AT70: 7462.2 | BB70: 17524 | BI70: 22508 | BJ70: 300731.15
L71: Coal on Water/Intransit (Barge,Vessel, Storage) | S71: 50733.86 | T71: 38024.75 | U71: 54428.51 | V71: 27826.88 | W71: 53569.77 | Y71: 37507.22 | AB71: 29774.12 | AJ71: 7521 | AT71: 7602.17 | AX71: 5099.93 | BB71: 47554 | BI71: 22505 | BJ71: 382147.21
L72: Cargo already completed on vessel during period | N72: 34354.25 | O72: 0 | P72: 0 | Q72: 40422.9 | R72: 691693.52 | S72: 238628.05 | T72: 93336.01 | U72: 428733.15 | V72: 125449.01 | W72: 115507.45 | X72: 0 | Y72: 165031.53 | Z72: 0 | AA72: 0 | AB72: 113075.49 | AC72: 22791.46 | AD72: 0 | AE72: 0 | AF72: 37500 | AG72: 0 | AH72: 105044.45 | AI72: 0 | AJ72: 15003 | AK72: 0 | AL72: 10235 | AM72: 0 | AN72: 0 | AO72: 0 | AP72: 0 | AQ72: 30036 | AR72: 0 | AS72: 0 | AT72: 22749.01 | AU72: 0 | AV72: 20362 | AW72: 4708.88 | AX72: 20324.9 | AY72: 0 | AZ72: 0 | BA72: 0 | BB72: 0 | BC72: 0 | BD72: 0 | BE72: 0 | BF72: 0 | BG72: 0 | BH72: 0 | BI72: 97375 | BJ72: 2432361.1
L73: Actual Crushing During Period | N73: 31631 | O73: 0 | P73: 0 | Q73: 37816 | R73: 571737 | S73: 205687.78 | T73: 100018.56 | U73: 443660.32 | V73: 184064.04 | W73: 164945.36 | X73: 0 | Y73: 192463 | Z73: 0 | AA73: 0 | AB73: 76294.17 | AC73: 15289.1 | AE73: 0 | AF73: 37500 | AG73: 0 | AH73: 67518.98 | AJ73: 15047 | AL73: 10235 | AM73: 0 | AQ73: 30036 | AS73: 0 | AT73: 22645.04 | AU73: 0 | AV73: 20362 | AW73: 0 | AX73: 10199.92 | AY73: 0 | AZ73: 0 | BA73: 0 | BB73: 65078 | BI73: 97520 | BJ73: 2399748.3
L74: Outlook FC Production (remain crushing) | N74: 0.42854161 | O74: 0 | P74: 0 | Q74: 0.19880685 | R74: 0.37265154 | S74: 0.22 | T74: 0.44 | U74: -0.32 | V74: 0.46 | W74: -0.36 | X74: 0 | Y74: 0 | Z74: 0 | AA74: 0 | AB74: 0.49 | AC74: 0 | AD74: 0 | AE74: 0 | AF74: 0 | AG74: 0 | AH74: 0 | AI74: 0 | AJ74: 0 | AK74: 0 | AL74: 0 | AM74: 0 | AN74: 0 | AO74: 0 | AP74: 0 | AQ74: 0 | AR74: 0 | AS74: 0 | AT74: 0 | AU74: 0 | AV74: 0 | AW74: 0 | AX74: 0 | AY74: 0 | AZ74: 0 | BA74: 0 | BB74: 0 | BC74: 0 | BD74: 0 | BE74: 0 | BF74: 0 | BG74: 0 | BH74: 0 | BI74: 0 | BJ74: 1.93
L75: Coal Supply Chain
L76: Prediction Ending Inventory | N76: 27282.389 | O76: 0 | P76: 0 | Q76: 33304.559 | R76: 132792.87 | S76: 131638.73 | T76: 136164.5 | U76: 154343.04 | V76: 101322.83 | W76: 125516.98 | X76: 1370.339 | Y76: 116657.12 | Z76: 0 | AA76: 0 | AB76: 47734.636 | AC76: 0 | AD76: 0 | AE76: 0 | AF76: 0 | AG76: 0 | AH76: 0 | AI76: 0 | AJ76: 7521 | AK76: 0 | AL76: 0 | AM76: 0 | AN76: 0 | AO76: 0 | AP76: 0 | AQ76: 0 | AR76: 0 | AS76: 0 | AT76: 15064.37 | AU76: 0 | AV76: 0 | AW76: 0 | AX76: 5099.93 | AY76: 0 | AZ76: 0 | BA76: 0 | BB76: 65078 | BC76: 0 | BD76: 0 | BE76: 0 | BF76: 0 | BG76: 0 | BH76: 0 | BI76: 45013 | BJ76: 1145904.3

Sheet Sheet2
A2: No | B2: Company | C2: End User | D2: Status | E2: TP Plan (MT) | F2: TP Actual (MT) | G2: Margin Plan ($) | H2: Margin Actual ($)
A3: 1 | B3: EBP | C3: PLNBN JUN #06 | D3: Match | E3: 55000 | F3: 55000 | G3: -718396.69 | H3: -675935.76
A4: 2 | B4: EBP | C4: TOSOH #03 | D4: Match | E4: 44200 | F4: 44200 | G4: 460892.15 | H4: 752606.99
A5: 3 | B5: IMM | C5: TNB JIMAH #3/6 | D5: Match | E5: 75000 | F5: 78700 | G5: 1737471.4 | H5: 2094872.4
A6: 4 | B6: EBP | C6: XINDIAN BAI GUI 5200NAR #10/19 | D6: Match | E6: 77000 | F6: 77000 | G6: -200929.62 | H6: -382341.93
A7: 5 | B7: EBP | C7: FREEPORT #1/4 | D7: Match | E7: 53000 | F7: 55600 | G7: 594734.54 | H7: 1122709
A8: 6 | B8: EBP | C8: TJ JATI IMM JUL #1 | D8: Match | E8: 67000 | F8: 67016 | G8: -581200.89 | H8: -296938.84
A9: 7 | B9: EBP | C9: XINDIAN BAI GUI 5200NAR #11/19 | D9: Match | E9: 70000 | F9: 73600 | G9: -416832.85 | H9: -498232.23
A10: 8 | B10: EBP | C10: PLNBN JUL #01 | D10: Match | E10: 55000 | F10: 52000 | G10: -785863.69 | H10: -695984.68
A11: 9 | B11: EBP | C11: SHENHUA 5200NAR TS 2% #4/6 | D11: Match | E11: 70000 | F11: 64999 | G11: -348520.21 | H11: -360876.16
A12: 10 | B12: EBP | C12: PLNBN JUL #02 | D12: Match | E12: 55000 | F12: 52000 | G12: -701937.58 | H12: -698299.63
A13: 11 | B13: EBP | C13: TJ JATI IMM JUL #2 | D13: Match | E13: 67000 | F13: 67007 | G13: -563191.54 | H13: -367957.73
A14: 12 | B14: EBP | C14: XINDIAN BAI GUI #3/7 (4450NAR) | D14: Match | E14: 70000 | F14: 63050 | G14: -459869.33 | H14: -601610.36
... A57: 55 | B57: EBP | C57: ZHEJIANG 5500NAR #4/5 | D57: Actual Only | E57: 0 | F57: 73450 | G57: 0 | H57: -685329.2

Sheet Sheet3
A2: Status | B2: Throughput Plan | C2: Throughput Actual | D2: Margin Plan | E2: Margin Actual
A3: Plan Only | B3: =SUMIF(Sheet2!D3:D58, "Plan Only", Sheet2!E3:E58) -> 383000 | C3: =SUMIF(Sheet2!D3:D58, "Plan Only",Sheet2!F3:F58) -> 0 | D3: =SUMIF(Sheet2!D3:D58, "Plan Only", Sheet2!G3:G58) -> -1513126.8 | E3: =SUMIF(Sheet2!D3:D58, "Plan Only", Sheet2!H3:H58) -> 0
A4: Match | B4: =SUMIF(Sheet2!D3:D58, "Match", Sheet2!E3:E58) -> 2166600 | C4: =SUMIF(Sheet2!D3:D58, "Match", Sheet2!F3:F58) -> 2146185.1 | D4: =SUMIF(Sheet2!D3:D58, "Match", Sheet2!G3:G58) -> 4717618.2 | E4: =SUMIF(Sheet2!D3:D58, "Match", Sheet2!H3:H58) -> 10817964
A5: Actual Only | B5: =SUMIF(Sheet2!D3:D58, Actual Only, Sheet2!E3:E58) -> 0 | C5: =SUMIF(Sheet2!D3:D58, "Actual Only",Sheet2!F3:F58) -> 286176 | D5: =SUMIF(Sheet2!D3:D58, "Actual Only", Sheet2!G3:G58) -> 0 | E5: =SUMIF(Sheet2!D3:D58, "Actual Only", Sheet2!H3:H58) -> -137603.59

Sheet Sheet4
A2: Month | B2: May
A5: Company | B5: Customer | C5: FOB Price Actual ($/ton) | D5: Margin Cash Actual ($/ton) | E5: Revenue Actual ($) | F5: Total Cost SSO Actual ($) | G5: Cash Margin Actual ($)
A6: BEK | B6: Kowepo | C6: 123.03 | D6: 40.722348 | E6: 9833173 | F6: -6578439.3 | G6: 3254733.7
A7: BEK | B7: TNB | C7: 122.97 | D7: 48.117436 | E7: 4156350 | F7: -2568474.6 | G7: 1587875.4
A8: IMM | B8: TNB | C8: 95.330013 | D8: 24.611884 | E8: 7892823 | F8: -5955867.8 | G8: 1936955.2
A9: TCM | B9: ITP | C9: 93.363302 | D9: 1.1230507 | E9: 710308 | F9: -701763.83 | G9: 8544.17
A10: EBP | B10: PLN | C10: 45.798425 | D10: -26.539966 | E10: 28303061 | F10: -44802507 | G10: -16499446
A11: EBP | B11: Hoping | C11: 107.51002 | D11: 3.2626237 | E11: 8282181 | F11: -8043389.6 | G11: 238791.43
A12: EBP | B12: Zhejiang | C12: 100.57685 | D12: 5.5497227 | E12: 29009478 | F12: -27425931 | G12: 1583546.8
A13: EBP | B13: Shenhua | C13: 97.979246 | D13: 11.498325 | E13: 14186273 | F13: -12553511 | G13: 1632762.2
A14: EBP | B14: Xindian | C14: 90.439523 | D14: 13.645851 | E14: 18898735 | F14: -15983299 | G14: 2915436.2
A15: EBP | B15: JERA | C15: 130.8184 | D15: 14.542893 | E15: 16785169 | F15: -14947238 | G15: 1837930.9
A16: EBP | B16: Sunny Express | C16: 93.970015 | D16: 15.244939 | E16: 5967651 | F16: -4976730 | G16: 990921.05
A17: EBP | B17: J-Power | C17: 129.96093 | D17: 15.478549 | E17: 18423236 | F17: -16277723 | G17: 2145512.6
... A21: EBP | B21: PTFI | C21: 137.00808 | D21: 28.535168 | E21: 7843627 | F21: -6257071.7 | G21: 1586555.3
A22: Grand Total | C22: 97.842839 | D22: 6.5943507 | E22: 240428374 | F22: -2.243914e+08 | G22: 16036973

Sheet Sheet5
B2: FOB Price Actual ($/ton) | C2: Margin Cash Actual ($/ton) | D2: Revenue Actual ($) | E2: Total Cost SSO Actual ($) | F2: Cash Margin Actual ($)
B3: 97.842839 | C3: 6.5943507 | D3: 240428374 | E3: -2.243914e+08 | F3: 16036973
